Workbook

Sheet 人员
A1: 序号 | B1: 姓名 | C1: 性别 | D1: 出生日期 | E1: 联系电话 | F1: 身份证号 | G1: 常驻地点 | H1: 证书编号 | I1: 毕业学校 | J1: 专业 | K1: 入职时间 | L1: 工作年限 | N1: 职责 | O1: 最终学历 | P1: 毕业时间 | Q1: 从业年限 | R1: 持有的项目管理类证书软件设计师 | S1: 持有的项目管理类证书网络工程师 | T1: 持有的项目管理类证书信息系统项目管理师 | U1: 持有的项目管理类证书系统分析师 | V1: 持有的项目管理类证书系统集成项目管理工程师 | W1: 持有的项目管理类证书系统规划与管理师 | X1: 持有的项目管理类证书数据库系统工程师 | Y1: 持有的项目管理类证书信息系统监理师 | Z1: 持有的网络安全类证书CISP | AA1: 持有的网络安全类证书CISAW | AB1: 持有的网络安全类证书CCSC | AC1: 持有的网络安全类证书CISSP | AD1: 持有的网络安全类证书Security+ | AE1: 持有的网络安全类证书渗透测试 | AF1: 持有的网络安全类证书等保测评 | AG1: 持有的网络安全类证书数据安全治理 | AH1: 持有的软件开发技术类证书软件评测师 | AI1: 持有的软件开发技术类证书云计算 | AJ1: 持有的软件开发技术类证书大数据 | AK1: 持有的软件开发技术类证书开发语言 | AL1: 持有的软件开发技术类证书架构设计 | AM1: 其他证书 | AN1: 证书编号 | AO1: 证书有效期 | AP1: 是否为本单位缴纳社保在职人员
A2: 1 | B2: 王宁 | C2: 男 | D2: AAAAAABBBBBB | E2: 139xxxxxxx | F2: =VLOOKUP(B2,所有人!A:Q,16,FALSE) -> 130423198804104713 | G2: =VLOOKUP(B2,所有人!A:Q,9,FALSE) -> 济南市 | I2: =VLOOKUP(B2,所有人!A:O,12,FALSE) -> 中国地质大学 | J2: =VLOOKUP(B2,所有人!A:O,14,FALSE) -> 土木工程 | K2: =VLOOKUP(B2,所有人!A:Q,17,FALSE) -> 2020/01/13 | L2: =DATEDIF(K2,TODAY(),"Y") -> 6 | M2: =VLOOKUP(B2,所有人!A:Q,7,FALSE) -> 解决方案经理 | N2: 项目经理 | O2: 本科 | P2: 2008/10/08 | Q2: 17 | T2: 2018201370103169 | AA2: 2018CISAWOM1210(R2) | AC2: 733056 | AP2: 是 | AQ2: =COUNTA(T2:AN2) -> 5
A3: 2 | B3: 朱冰霞 | C3: 男 | D3: AAAAAABBBBBB | E3: 139xxxxxxx | F3: =VLOOKUP(B3,所有人!A:Q,16,FALSE) -> 440582199608155145 | G3: =VLOOKUP(B3,所有人!A:Q,9,FALSE) -> 广州市 | I3: =VLOOKUP(B3,所有人!A:O,12,FALSE) -> 广州大学华软软件学院 | J3: =VLOOKUP(B3,所有人!A:O,14,FALSE) -> 行政管理 | K3: =VLOOKUP(B3,所有人!A:Q,17,FALSE) -> 2021/04/21 | L3: =DATEDIF(K3,TODAY(),"Y") -> 5 | M3: =VLOOKUP(B3,所有人!A:Q,7,FALSE) -> 跨专业支持工程师 | N3: 项目经理 | O3: 本科 | P3: 2017/05/15 | Q3: 9 | T3: 31420201144010108636 | Z3: CNITSEC2021CISO24387 | AA3: 2024CISAWES0060 | AP3: 是 | AQ3: =COUNTA(T3:AN3) -> 4
A4: 3 | B4: 纪晓乐 | C4: 男 | D4: AAAAAABBBBBB | E4: 139xxxxxxx | F4: =VLOOKUP(B4,所有人!A:Q,16,FALSE) -> 372321198610058964 | G4: =VLOOKUP(B4,所有人!A:Q,9,FALSE) -> 天津市 | I4: =VLOOKUP(B4,所有人!A:O,12,FALSE) -> 天津职业技术师范大学 | J4: =VLOOKUP(B4,所有人!A:O,14,FALSE) -> 计算机科学与技术 | K4: =VLOOKUP(B4,所有人!A:Q,17,FALSE) -> 2017/06/01 | L4: =DATEDIF(K4,TODAY(),"Y") -> 9 | M4: =VLOOKUP(B4,所有人!A:Q,7,FALSE) -> 系统运营专家 | N4: 项目实施人员 | O4: 本科 | P4: 2011/07/01 | Q4: 14 | T4: 31420201112000100140 | Z4: CNITSEC2022CISO17999 | AP4: 是 | AQ4: =COUNTA(T4:AN4) -> 2
A5: 4 | B5: 崔宇 | C5: 男 | D5: AAAAAABBBBBB | E5: 139xxxxxxx | F5: =VLOOKUP(B5,所有人!A:Q,16,FALSE) -> 211224198309152415 | G5: =VLOOKUP(B5,所有人!A:Q,9,FALSE) -> 成都市 | I5: =VLOOKUP(B5,所有人!A:O,12,FALSE) -> 电子科技大学 | J5: =VLOOKUP(B5,所有人!A:O,14,FALSE) -> 通信工程 | K5: =VLOOKUP(B5,所有人!A:Q,17,FALSE) -> 2017/01/10 | L5: =DATEDIF(K5,TODAY(),"Y") -> 9 | M5: =VLOOKUP(B5,所有人!A:Q,7,FALSE) -> 实施运维工程师 | N5: 架构师 | O5: 本科 | P5: 2008/09/01 | Q5: 17 | T5: 31420190551010108532 | AA5: 2020CISAWSI3056 (R) | AP5: 是 | AQ5: =COUNTA(T5:AN5) -> 2
A6: 5 | B6: 李大健 | C6: 男 | D6: AAAAAABBBBBB | E6: 139xxxxxxx | F6: =VLOOKUP(B6,所有人!A:Q,16,FALSE) -> 22038119860619181X | G6: =VLOOKUP(B6,所有人!A:Q,9,FALSE) -> 杭州市 | I6: =VLOOKUP(B6,所有人!A:O,12,FALSE) -> 郑州轻工业学院 | J6: =VLOOKUP(B6,所有人!A:O,14,FALSE) -> 自动化 | K6: =VLOOKUP(B6,所有人!A:Q,17,FALSE) -> 2019/09/02 | L6: =DATEDIF(K6,TODAY(),"Y") -> 6 | M6: =VLOOKUP(B6,所有人!A:Q,7,FALSE) -> 系统运营经理 | N6: 质控工程师 | O6: 本科 | P6: 2010/07/01 | Q6: 15 | T6: 31420201133000103745 | AP6: 是 | AQ6: =COUNTA(T6:AN6) -> 1
A7: 6 | B7: 王鑫1 | C7: 男 | D7: AAAAAABBBBBB | E7: 139xxxxxxx | F7: =VLOOKUP(B7,所有人!A:Q,16,FALSE) -> 230107199209092473 | G7: =VLOOKUP(B7,所有人!A:Q,9,FALSE) -> 哈尔滨市 | I7: =VLOOKUP(B7,所有人!A:O,12,FALSE) -> 哈尔滨理工大学 | J7: =VLOOKUP(B7,所有人!A:O,14,FALSE) -> 计算机科学与技术 | K7: =VLOOKUP(B7,所有人!A:Q,17,FALSE) -> 2023/01/10 | L7: =DATEDIF(K7,TODAY(),"Y") -> 3 | M7: =VLOOKUP(B7,所有人!A:Q,7,FALSE) -> 解决方案经理 | N7: 项目经理 | O7: 本科 | P7: 2015/07/01 | Q7: 10 | T7: 31420201123010101611 | Z7: CNITSEC2017CISE01334 | AP7: 是 | AQ7: =COUNTA(T7:AN7) -> 2
A8: 7 | B8: 王泽君 | C8: 男 | D8: AAAAAABBBBBB | E8: 139xxxxxxx | F8: =VLOOKUP(B8,所有人!A:Q,16,FALSE) -> 42122119951201002X | G8: =VLOOKUP(B8,所有人!A:Q,9,FALSE) -> 海口市 | I8: =VLOOKUP(B8,所有人!A:O,12,FALSE) -> 上海海洋大学 | J8: =VLOOKUP(B8,所有人!A:O,14,FALSE) -> 物流工程 | K8: =VLOOKUP(B8,所有人!A:Q,17,FALSE) -> 2026/03/02 | L8: =DATEDIF(K8,TODAY(),"Y") -> 0 | M8: =VLOOKUP(B8,所有人!A:Q,7,FALSE) -> 系统运营经理 | N8: 项目经理 | O8: 本科 | P8: 2017/06/30 | Q8: 8 | T8: 31420211146010105177 | AP8: 是 | AQ8: =COUNTA(T8:AN8) -> 1
A9: 8 | B9: 范志华 | C9: 男 | D9: AAAAAABBBBBB | E9: 139xxxxxxx | F9: =VLOOKUP(B9,所有人!A:Q,16,FALSE) -> 412721198109041434 | G9: =VLOOKUP(B9,所有人!A:Q,9,FALSE) -> 济南市 | I9: =VLOOKUP(B9,所有人!A:O,12,FALSE) -> 江西财经理工学院 | J9: =VLOOKUP(B9,所有人!A:O,14,FALSE) -> 计算机 | K9: =VLOOKUP(B9,所有人!A:Q,17,FALSE) -> 2015/12/28 | L9: =DATEDIF(K9,TODAY(),"Y") -> 10 | M9: =VLOOKUP(B9,所有人!A:Q,7,FALSE) -> 系统运营经理 | N9: 项目经理 | O9: 大专及其以下 | P9: 2003/12/01 | Q9: 23 | T9: 31420191137010103072 | Z9: CNITSEC2022CISE05441 | AA9: 2020CISAWSI3056 (R) | AQ9: =COUNTA(T9:AN9) -> 3
A10: 9 | B10: 朱海楠 | C10: 男 | D10: AAAAAABBBBBB | E10: 139xxxxxxx | F10: =VLOOKUP(B10,所有人!A:Q,16,FALSE) -> 120222198804253824 | G10: =VLOOKUP(B10,所有人!A:Q,9,FALSE) -> 天津市 | I10: =VLOOKUP(B10,所有人!A:O,12,FALSE) -> 天津理工大学 | J10: =VLOOKUP(B10,所有人!A:O,14,FALSE) -> 信息与计算科学 | K10: =VLOOKUP(B10,所有人!A:Q,17,FALSE) -> 2023/10/09 | L10: =DATEDIF(K10,TODAY(),"Y") -> 2 | M10: =VLOOKUP(B10,所有人!A:Q,7,FALSE) -> 系统运营经理 | N10: 项目实施人员 | O10: 本科 | P10: 2011/10/10 | Q10: 15 | T10: 17201120097 | AQ10: =COUNTA(T10:AN10) -> 1
A11: 10 | B11: 赵卫斌1 | C11: 男 | D11: AAAAAABBBBBB | E11: 139xxxxxxx | F11: =VLOOKUP(B11,所有人!A:Q,16,FALSE) -> 410826198105183537 | G11: =VLOOKUP(B11,所有人!A:Q,9,FALSE) -> 郑州市 | I11: =VLOOKUP(B11,所有人!A:O,12,FALSE) -> 北京外国语大学 | J11: =VLOOKUP(B11,所有人!A:O,14,FALSE) -> 英语 | K11: =VLOOKUP(B11,所有人!A:Q,17,FALSE) -> 2023/12/04 | L11: =DATEDIF(K11,TODAY(),"Y") -> 2 | M11: =VLOOKUP(B11,所有人!A:Q,7,FALSE) -> 实施运维工程师 | N11: 质控工程师 | O11: 本科 | P11: 2002/05/08 | Q11: 24 | T11: 31420191141010103684 | AQ11: =COUNTA(T11:AN11) -> 1
A12: 11 | B12: 陈宇 | C12: 男 | D12: AAAAAABBBBBB | E12: 139xxxxxxx | F12: =VLOOKUP(B12,所有人!A:Q,16,FALSE) -> 150103197505051030 | G12: =VLOOKUP(B12,所有人!A:Q,9,FALSE) -> 呼和浩特市 | I12: =VLOOKUP(B12,所有人!A:O,12,FALSE) -> 内蒙古大学 | J12: =VLOOKUP(B12,所有人!A:O,14,FALSE) -> 工商管理 | K12: =VLOOKUP(B12,所有人!A:Q,17,FALSE) -> 2020/09/14 | L12: =DATEDIF(K12,TODAY(),"Y") -> 5 | M12: =VLOOKUP(B12,所有人!A:Q,7,FALSE) -> 解决方案经理 | N12: 项目经理 | O12: 硕士研究生 | P12: 1998/09/01 | Q12: 27 | T12: 13101150015 | Z12: CNITSEC2023CISP-DSG18521 | AM12: PMP | AN12: 49810 | AP12: 是 | AQ12: =COUNTA(T12:AN12) -> 5
A13: 12 | B13: 崔渊博 | C13: 男 | D13: AAAAAABBBBBB | E13: 139xxxxxxx | F13: =VLOOKUP(B13,所有人!A:Q,16,FALSE) -> 413028198110273010 | G13: =VLOOKUP(B13,所有人!A:Q,9,FALSE) -> 北京市 | I13: =VLOOKUP(B13,所有人!A:O,12,FALSE) -> 东北大学 | J13: =VLOOKUP(B13,所有人!A:O,14,FALSE) -> 计算机系统结构 | K13: =VLOOKUP(B13,所有人!A:Q,17,FALSE) -> 2015/06/10 | L13: =DATEDIF(K13,TODAY(),"Y") -> 11 | M13: =VLOOKUP(B13,所有人!A:Q,7,FALSE) -> 部门总监 | N13: 架构师 | O13: 硕士研究生 | P13: 2006/02/14 | Q13: 20 | T13: 16101110794 | Z13: CNITSEC2019CISE04325 | AA13: 2023CISAWSS0420 | AP13: 是 | AQ13: =COUNTA(T13:AN13) -> 3
A14: 13 | B14: 李跃波 | C14: 男 | D14: AAAAAABBBBBB | E14: 139xxxxxxx | F14: =VLOOKUP(B14,所有人!A:Q,16,FALSE) -> 13042919820412003X | G14: =VLOOKUP(B14,所有人!A:Q,9,FALSE) -> 太原市 | I14: =VLOOKUP(B14,所有人!A:O,12,FALSE) -> 郑州大学 | J14: =VLOOKUP(B14,所有人!A:O,14,FALSE) -> 计算机科学与技术 | K14: =VLOOKUP(B14,所有人!A:Q,17,FALSE) -> 2021/03/30 | L14: =DATEDIF(K14,TODAY(),"Y") -> 5 | M14: =VLOOKUP(B14,所有人!A:Q,7,FALSE) -> 项目经理 | N14: 项目实施人员 | O14: 本科 | P14: 2005/08/01 | Q14: 20 | T14: 15006923 | AA14: 2023CSAWSI0952 | AM14: PMP | AN14: 2966782 | AP14: 是 | AQ14: =COUNTA(T14:AN14) -> 5
A15: 14 | B15: 胡兵 | C15: 男 | D15: AAAAAABBBBBB | E15: 139xxxxxxx | F15: =VLOOKUP(B15,所有人!A:Q,16,FALSE) -> 440232198508120012 | G15: =VLOOKUP(B15,所有人!A:Q,9,FALSE) -> 北京市 | I15: =VLOOKUP(B15,所有人!A:O,12,FALSE) -> 北京理工大学 | J15: =VLOOKUP(B15,所有人!A:O,14,FALSE) -> 网络工程 | K15: =VLOOKUP(B15,所有人!A:Q,17,FALSE) -> 2011/06/16 | L15: =DATEDIF(K15,TODAY(),"Y") -> 15 | M15: =VLOOKUP(B15,所有人!A:Q,7,FALSE) -> 副总裁兼事业部副总经理 | N15: 项目实施人员 | O15: 本科 | P15: 2008/03/01 | Q15: 18 | Z15: CNITSEC2014CISE01881 | AP15: 是 | AQ15: =COUNTA(T15:AN15) -> 3
A16: 15 | B16: 吴涛 | C16: 男 | D16: AAAAAABBBBBB | E16: 139xxxxxxx | F16: =VLOOKUP(B16,所有人!A:Q,16,FALSE) -> 110105198112152113 | G16: =VLOOKUP(B16,所有人!A:Q,9,FALSE) -> 北京市 | I16: =VLOOKUP(B16,所有人!A:O,12,FALSE) -> 北京国际商务学院 | J16: =VLOOKUP(B16,所有人!A:O,14,FALSE) -> 计算机网络管理 | K16: =VLOOKUP(B16,所有人!A:Q,17,FALSE) -> 2011/04/15 | L16: =DATEDIF(K16,TODAY(),"Y") -> 15 | M16: =VLOOKUP(B16,所有人!A:Q,7,FALSE) -> 中心副总经理 | N16: 项目实施人员 | O16: 本科 | P16: 2000/07/01 | Q16: 25 | Z16: CNITSEC2019CISE08096 | AA16: 2020CISAWSI2995(R) | AP16: 是 | AQ16: =COUNTA(T16:AN16) -> 3
A17: 16 | B17: 林阳 | C17: 男 | D17: AAAAAABBBBBB | E17: 139xxxxxxx | F17: =VLOOKUP(B17,所有人!A:Q,16,FALSE) -> 360301199402180012 | G17: =VLOOKUP(B17,所有人!A:Q,9,FALSE) -> 北京市 | I17: =VLOOKUP(B17,所有人!A:O,12,FALSE) -> 华中科技大学文华学院 | J17: =VLOOKUP(B17,所有人!A:O,14,FALSE) -> 通信工程 | K17: =VLOOKUP(B17,所有人!A:Q,17,FALSE) -> 2016/06/23 | L17: =DATEDIF(K17,TODAY(),"Y") -> 10 | M17: =VLOOKUP(B17,所有人!A:Q,7,FALSE) -> 项目经理 | N17: 项目经理 | O17: 本科 | P17: 2016/06/23 | Q17: 9 | Z17: CNITSEC2021CISE22549 | AA17: 2023CISAWSI0944 | AM17: PMP | AN17: 2945160 | AP17: 是 | AQ17: =COUNTA(T17:AN17) -> 4
A18: 17 | B18: 史祥鹏 | C18: 男 | D18: AAAAAABBBBBB | E18: 139xxxxxxx | F18: =VLOOKUP(B18,所有人!A:Q,16,FALSE) -> 622425198210131213 | G18: =VLOOKUP(B18,所有人!A:Q,9,FALSE) -> 兰州市 | I18: =VLOOKUP(B18,所有人!A:O,12,FALSE) -> 中国管理软件学院 | J18: =VLOOKUP(B18,所有人!A:O,14,FALSE) -> 计算机软件及应用 | K18: =VLOOKUP(B18,所有人!A:Q,17,FALSE) -> 2010/11/01 | L18: =DATEDIF(K18,TODAY(),"Y") -> 15 | M18: =VLOOKUP(B18,所有人!A:Q,7,FALSE) -> 部门总监 | N18: 项目实施人员 | O18: 本科 | P18: 2006/01/01 | Q18: 20 | AA18: 2020CSAWOM2667(R) | AP18: 是 | AQ18: =COUNTA(T18:AN18) -> 3
A19: 18 | B19: 张利强 | C19: 男 | D19: AAAAAABBBBBB | E19: 139xxxxxxx | F19: =VLOOKUP(B19,所有人!A:Q,16,FALSE) -> 650103197809202318 | G19: =VLOOKUP(B19,所有人!A:Q,9,FALSE) -> 乌鲁木齐市 | I19: =VLOOKUP(B19,所有人!A:O,12,FALSE) -> 大连理工大学 | J19: =VLOOKUP(B19,所有人!A:O,14,FALSE) -> 电子与通信工程 | K19: =VLOOKUP(B19,所有人!A:Q,17,FALSE) -> 2020/09/01 | L19: =DATEDIF(K19,TODAY(),"Y") -> 5 | M19: =VLOOKUP(B19,所有人!A:Q,7,FALSE) -> 区域首席客户经理 | N19: 测试人员 | O19: 本科 | P19: 2001/07/01 | Q19: 24 | AA19: 2023CISAWSI0958 | AM19: PMP | AN19: 509061 | AP19: 是 | AQ19: =COUNTA(T19:AN19) -> 4
A20: 19 | B20: 刘晟鑫 | C20: 男 | D20: AAAAAABBBBBB | E20: 139xxxxxxx | F20: =VLOOKUP(B20,所有人!A:Q,16,FALSE) -> 340503198705090415 | G20: =VLOOKUP(B20,所有人!A:Q,9,FALSE) -> 广州市 | I20: =VLOOKUP(B20,所有人!A:O,12,FALSE) -> 中国人民大学 | J20: =VLOOKUP(B20,所有人!A:O,14,FALSE) -> 工商管理 | K20: =VLOOKUP(B20,所有人!A:Q,17,FALSE) -> 2011/09/01 | L20: =DATEDIF(K20,TODAY(),"Y") -> 14 | M20: =VLOOKUP(B20,所有人!A:Q,7,FALSE) -> 部门总监 | N20: 需求分析专家 | O20: 本科 | P20: 2009/07/01 | Q20: 16 | Z20: CNITSEC2019CISE04352 | AA20: 2020CISAWSI2955(R) | AP20: 是 | AQ20: =COUNTA(T20:AN20) -> 3
A21: 20 | B21: 王龙 | C21: 男 | D21: AAAAAABBBBBB | E21: 139xxxxxxx | F21: =VLOOKUP(B21,所有人!A:Q,16,FALSE) -> 230227199207170811 | G21: =VLOOKUP(B21,所有人!A:Q,9,FALSE) -> 北京市 | I21: =VLOOKUP(B21,所有人!A:O,12,FALSE) -> 佳木斯大学 | J21: =VLOOKUP(B21,所有人!A:O,14,FALSE) -> 通信工程 | K21: =VLOOKUP(B21,所有人!A:Q,17,FALSE) -> 2014/07/01 | L21: =DATEDIF(K21,TODAY(),"Y") -> 11 | M21: =VLOOKUP(B21,所有人!A:Q,7,FALSE) -> Java工程师 | N21: 质控工程师 | O21: 本科 | P21: 2014/07/01 | Q21: 11 | AM21: PMP | AN21: 2619774 | AP21: 是 | AQ21: =COUNTA(T21:AN21) -> 4
A22: 21 | B22: 董清辉 | C22: 男 | D22: AAAAAABBBBBB | E22: 139xxxxxxx | F22: =VLOOKUP(B22,所有人!A:Q,16,FALSE) -> 130731198604130630 | G22: =VLOOKUP(B22,所有人!A:Q,9,FALSE) -> 北京市 | I22: =VLOOKUP(B22,所有人!A:O,12,FALSE) -> 北京邮电大学 | J22: =VLOOKUP(B22,所有人!A:O,14,FALSE) -> 计算机科学与技术 | K22: =VLOOKUP(B22,所有人!A:Q,17,FALSE) -> 2015/12/28 | L22: =DATEDIF(K22,TODAY(),"Y") -> 10 | M22: =VLOOKUP(B22,所有人!A:Q,7,FALSE) -> 系统可靠性监测专家 | N22: 项目实施人员 | O22: 本科 | P22: 2008/07/01 | Q22: 17 | Z22: CNITSEC2019CISE04353 | AA22: 2017CISAWES0219 (R3) | AP22: 是 | AQ22: =COUNTA(T22:AN22) -> 3
A23: 22 | B23: 袁林 | C23: 男 | D23: AAAAAABBBBBB | E23: 139xxxxxxx | F23: =VLOOKUP(B23,所有人!A:Q,16,FALSE) -> 210204197611055332 | G23: =VLOOKUP(B23,所有人!A:Q,9,FALSE) -> 大连市 | I23: =VLOOKUP(B23,所有人!A:O,12,FALSE) -> 辽宁师范大学 | J23: =VLOOKUP(B23,所有人!A:O,14,FALSE) -> 应用电子技术 | K23: =VLOOKUP(B23,所有人!A:Q,17,FALSE) -> 2017/09/01 | L23: =DATEDIF(K23,TODAY(),"Y") -> 8 | M23: =VLOOKUP(B23,所有人!A:Q,7,FALSE) -> 中心副总经理 | N23: 测试人员 | O23: 本科 | P23: 1999/07/22 | Q23: 26 | Z23: CNITSEC2019CISE04334 | AP23: 是 | AQ23: =COUNTA(T23:AN23) -> 3
A24: 23 | B24: 刘武旭 | C24: 男 | D24: AAAAAABBBBBB | E24: 139xxxxxxx | F24: =VLOOKUP(B24,所有人!A:Q,16,FALSE) -> 412725198512126978 | G24: =VLOOKUP(B24,所有人!A:Q,9,FALSE) -> 郑州市 | I24: =VLOOKUP(B24,所有人!A:O,12,FALSE) -> 河南工业大学 | J24: =VLOOKUP(B24,所有人!A:O,14,FALSE) -> 计算机科学与技术 | K24: =VLOOKUP(B24,所有人!A:Q,17,FALSE) -> 2015/08/21 | L24: =DATEDIF(K24,TODAY(),"Y") -> 10 | M24: =VLOOKUP(B24,所有人!A:Q,7,FALSE) -> 客户总监 | N24: 项目经理 | O24: 本科 | P24: 2008/08/01 | Q24: 17 | Z24: CNITSEC2019CISE04376 | AA24: 2023CISAWSS0384 | AM24: PMP | AN24: 3082489 | AP24: 是 | AQ24: =COUNTA(T24:AN24) -> 4
A25: 24 | B25: 邸学锋 | C25: 男 | D25: AAAAAABBBBBB | E25: 139xxxxxxx | F25: =VLOOKUP(B25,所有人!A:Q,16,FALSE) -> 510108197603101539 | G25: =VLOOKUP(B25,所有人!A:Q,9,FALSE) -> 大连市 | I25: =VLOOKUP(B25,所有人!A:O,12,FALSE) -> 电子科技大学 | J25: =VLOOKUP(B25,所有人!A:O,14,FALSE) -> 计算机通信 | K25: =VLOOKUP(B25,所有人!A:Q,17,FALSE) -> 2017/08/10 | L25: =DATEDIF(K25,TODAY(),"Y") -> 8 | M25: =VLOOKUP(B25,所有人!A:Q,7,FALSE) -> C语言工程师 | N25: 质控工程师 | O25: 本科 | P25: 1999/07/01 | Q25: 26 | Z25: CNITSEC2019CISE04335 | AP25: 是 | AQ25: =COUNTA(T25:AN25) -> 3
A26: 25 | B26: 姚瑞 | C26: 男 | D26: AAAAAABBBBBB | E26: 139xxxxxxx | F26: =VLOOKUP(B26,所有人!A:Q,16,FALSE) -> 130726199005084517 | G26: =VLOOKUP(B26,所有人!A:Q,9,FALSE) -> 北京市 | I26: =VLOOKUP(B26,所有人!A:O,12,FALSE) -> 哈尔滨华德学院 | J26: =VLOOKUP(B26,所有人!A:O,14,FALSE) -> 自动化 | K26: =VLOOKUP(B26,所有人!A:Q,17,FALSE) -> 2018/04/08 | L26: =DATEDIF(K26,TODAY(),"Y") -> 8 | M26: =VLOOKUP(B26,所有人!A:Q,7,FALSE) -> Java工程师 | N26: 项目实施人员 | O26: 本科 | P26: 2014/08/08 | Q26: 11 | AM26: PMP | AN26: 2628281 | AP26: 是 | AQ26: =COUNTA(T26:AN26) -> 4
A27: 26 | B27: 贾立军 | C27: 男 | D27: AAAAAABBBBBB | E27: 139xxxxxxx | F27: =VLOOKUP(B27,所有人!A:Q,16,FALSE) -> 21132419820307301X | G27: =VLOOKUP(B27,所有人!A:Q,9,FALSE) -> 大连市 | I27: =VLOOKUP(B27,所有人!A:O,12,FALSE) -> 中央广播电视大学 | J27: =VLOOKUP(B27,所有人!A:O,14,FALSE) -> 计算机科学与技术 | K27: =VLOOKUP(B27,所有人!A:Q,17,FALSE) -> 2017/09/01 | L27: =DATEDIF(K27,TODAY(),"Y") -> 8 | M27: =VLOOKUP(B27,所有人!A:Q,7,FALSE) -> 组长 | N27: 测试人员 | O27: 本科 | P27: 2004/07/08 | Q27: 21 | Z27: CNITSEC2019CISE04337 | AP27: 是 | AQ27: =COUNTA(T27:AN27) -> 3
A28: 27 | B28: 刘道林 | C28: 男 | D28: AAAAAABBBBBB | E28: 139xxxxxxx | F28: =VLOOKUP(B28,所有人!A:Q,16,FALSE) -> 210204198206286772 | G28: =VLOOKUP(B28,所有人!A:Q,9,FALSE) -> 大连市 | I28: =VLOOKUP(B28,所有人!A:O,12,FALSE) -> 大连工业大学 | J28: =VLOOKUP(B28,所有人!A:O,14,FALSE) -> 机械设计及理论 | K28: =VLOOKUP(B28,所有人!A:Q,17,FALSE) -> 2019/06/03 | L28: =DATEDIF(K28,TODAY(),"Y") -> 7 | M28: =VLOOKUP(B28,所有人!A:Q,7,FALSE) -> 部门副总监 | N28: 项目经理 | O28: 硕士研究生 | P28: 2008/04/21 | Q28: 18 | Z28: CNITSEC2019CISE04340 | AP28: 是 | AQ28: =COUNTA(T28:AN28) -> 3
A29: 28 | B29: 苏万龙 | C29: 男 | D29: AAAAAABBBBBB | E29: 139xxxxxxx | F29: =VLOOKUP(B29,所有人!A:Q,16,FALSE) -> 230182198701244219 | G29: =VLOOKUP(B29,所有人!A:Q,9,FALSE) -> 广州市 | I29: =VLOOKUP(B29,所有人!A:O,12,FALSE) -> 广西工学院鹿山学院 | J29: =VLOOKUP(B29,所有人!A:O,14,FALSE) -> 电子信息工程 | K29: =VLOOKUP(B29,所有人!A:Q,17,FALSE) -> 2021/06/15 | L29: =DATEDIF(K29,TODAY(),"Y") -> 5 | M29: =VLOOKUP(B29,所有人!A:Q,7,FALSE) -> 项目经理 | N29: 架构师 | O29: 本科 | P29: 2011/01/24 | Q29: 15 | Z29: CNTSECICSO18 | AA29: 2024CISAWES0004 | AP29: 是 | AQ29: =COUNTA(T29:AN29) -> 3
A30: 29 | B30: 张俊 | C30: 男 | D30: AAAAAABBBBBB | E30: 139xxxxxxx | F30: =VLOOKUP(B30,所有人!A:Q,16,FALSE) -> 320482198808301816 | G30: =VLOOKUP(B30,所有人!A:Q,9,FALSE) -> 南京市 | I30: =VLOOKUP(B30,所有人!A:O,12,FALSE) -> 南京大学 | J30: =VLOOKUP(B30,所有人!A:O,14,FALSE) -> 软件工程 | K30: =VLOOKUP(B30,所有人!A:Q,17,FALSE) -> 2010/07/26 | L30: =DATEDIF(K30,TODAY(),"Y") -> 15 | M30: =VLOOKUP(B30,所有人!A:Q,7,FALSE) -> 项目经理 | N30: 需求分析专家 | O30: 本科 | P30: 2010/07/07 | Q30: 15 | Z30: CNITSEC2019CISE04359 | AA30: 2020CISAWSI2947 (R) | AM30: PMP | AN30: 1634623 | AP30: 是 | AQ30: =COUNTA(T30:AN30) -> 4
A31: 30 | B31: 范磊波 | C31: 男 | D31: AAAAAABBBBBB | E31: 139xxxxxxx | F31: =VLOOKUP(B31,所有人!A:Q,16,FALSE) -> 430124199007167119 | G31: =VLOOKUP(B31,所有人!A:Q,9,FALSE) -> 武汉市 | I31: =VLOOKUP(B31,所有人!A:O,12,FALSE) -> 湖南城市学院 | J31: =VLOOKUP(B31,所有人!A:O,14,FALSE) -> 信息与技术科学 | K31: =VLOOKUP(B31,所有人!A:Q,17,FALSE) -> 2017/04/05 | L31: =DATEDIF(K31,TODAY(),"Y") -> 9 | M31: =VLOOKUP(B31,所有人!A:Q,7,FALSE) -> 组长 | N31: 测试人员 | O31: 本科 | P31: 2013/11/17 | Q31: 12 | Z31: CNTTSEC2023CISO12148 | AA31: 2018CISAWSS0446 (R2) | AM31: PMP | AN31: 3481341 | AP31: 是 | AQ31: =COUNTA(T31:AN31) -> 4
A32: 31 | B32: 季斌 | C32: 男 | D32: AAAAAABBBBBB | E32: 139xxxxxxx | F32: =VLOOKUP(B32,所有人!A:Q,16,FALSE) -> 370121197511037714 | G32: =VLOOKUP(B32,所有人!A:Q,9,FALSE) -> 济南市 | I32: =VLOOKUP(B32,所有人!A:O,12,FALSE) -> 北京外国语大学 | J32: =VLOOKUP(B32,所有人!A:O,14,FALSE) -> 英语 | K32: =VLOOKUP(B32,所有人!A:Q,17,FALSE) -> 2021/05/14 | L32: =DATEDIF(K32,TODAY(),"Y") -> 5 | M32: =VLOOKUP(B32,所有人!A:Q,7,FALSE) -> 区域首席客户经理 | N32: 项目实施人员 | O32: 本科 | P32: 1999/09/01 | Q32: 26 | AM32: PMP | AN32: 2828477 | AP32: 是 | AQ32: =COUNTA(T32:AN32) -> 4
A33: 32 | B33: 常宁 | C33: 男 | D33: AAAAAABBBBBB | E33: 139xxxxxxx | F33: =VLOOKUP(B33,所有人!A:Q,16,FALSE) -> 411381198911227133 | G33: =VLOOKUP(B33,所有人!A:Q,9,FALSE) -> 武汉市 | I33: =VLOOKUP(B33,所有人!A:O,12,FALSE) -> 黄河科技学院 | J33: =VLOOKUP(B33,所有人!A:O,14,FALSE) -> 计算机科学与技术 | K33: =VLOOKUP(B33,所有人!A:Q,17,FALSE) -> 2015/04/13 | L33: =DATEDIF(K33,TODAY(),"Y") -> 11 | M33: =VLOOKUP(B33,所有人!A:Q,7,FALSE) -> 组长 | N33: 项目实施人员 | O33: 本科 | P33: 2012/09/15 | Q33: 13 | AM33: PMP | AN33: 3293034 | AP33: 是 | AQ33: =COUNTA(T33:AN33) -> 4
A34: 33 | B34: 钱奇 | C34: 男 | D34: AAAAAABBBBBB | E34: 139xxxxxxx | F34: =VLOOKUP(B34,所有人!A:Q,16,FALSE) -> 342601199110114675 | G34: =VLOOKUP(B34,所有人!A:Q,9,FALSE) -> 北京市 | I34: =VLOOKUP(B34,所有人!A:O,12,FALSE) -> 辽宁大学 | J34: =VLOOKUP(B34,所有人!A:O,14,FALSE) -> 计算机科学与技术 | K34: =VLOOKUP(B34,所有人!A:Q,17,FALSE) -> 2017/07/05 | L34: =DATEDIF(K34,TODAY(),"Y") -> 8 | M34: =VLOOKUP(B34,所有人!A:Q,7,FALSE) -> Java工程师 | N34: 项目经理 | O34: 本科 | P34: 2018/07/01 | Q34: 7 | AM34: PMP | AN34: 2253769 | AP34: 是 | AQ34: =COUNTA(T34:AN34) -> 4
A35: 34 | B35: 董晓晖 | C35: 男 | D35: AAAAAABBBBBB | E35: 139xxxxxxx | F35: =VLOOKUP(B35,所有人!A:Q,16,FALSE) -> 37068219891221021X | G35: =VLOOKUP(B35,所有人!A:Q,9,FALSE) -> 济南市 | I35: =VLOOKUP(B35,所有人!A:O,12,FALSE) -> 南京邮电大学通达学院 | J35: =VLOOKUP(B35,所有人!A:O,14,FALSE) -> 计算机科学与技术 | K35: =VLOOKUP(B35,所有人!A:Q,17,FALSE) -> 2016/08/22 | L35: =DATEDIF(K35,TODAY(),"Y") -> 9 | M35: =VLOOKUP(B35,所有人!A:Q,7,FALSE) -> 实施运维工程师 | N35: 测试人员 | O35: 本科 | P35: 2013/07/16 | Q35: 12 | AM35: PMP | AN35: 1893703 | AP35: 是 | AQ35: =COUNTA(T35:AN35) -> 4
A36: 35 | B36: 李宁 | C36: 男 | D36: AAAAAABBBBBB | E36: 139xxxxxxx | F36: =VLOOKUP(B36,所有人!A:Q,16,FALSE) -> 420901199107071111 | G36: =VLOOKUP(B36,所有人!A:Q,9,FALSE) -> 重庆市 | I36: =VLOOKUP(B36,所有人!A:O,12,FALSE) -> 三峡大学 | J36: =VLOOKUP(B36,所有人!A:O,14,FALSE) -> 工程管理 | K36: =VLOOKUP(B36,所有人!A:Q,17,FALSE) -> 2021/06/15 | L36: =DATEDIF(K36,TODAY(),"Y") -> 5 | M36: =VLOOKUP(B36,所有人!A:Q,7,FALSE) -> 区域首席客户经理 | N36: 项目实施人员 | O36: 本科 | P36: 2014/10/02 | Q36: 11 | Z36: CNITSEC2022CISE05642 | AP36: 是 | AQ36: =COUNTA(T36:AN36) -> 3
A37: 36 | B37: 许延一 | C37: 男 | D37: AAAAAABBBBBB | E37: 139xxxxxxx | F37: =VLOOKUP(B37,所有人!A:Q,16,FALSE) -> 130533199303076411 | G37: =VLOOKUP(B37,所有人!A:Q,9,FALSE) -> 北京市 | I37: =VLOOKUP(B37,所有人!A:O,12,FALSE) -> 河北科技师范学院 | J37: =VLOOKUP(B37,所有人!A:O,14,FALSE) -> 网络工程 | K37: =VLOOKUP(B37,所有人!A:Q,17,FALSE) -> 2016/08/16 | L37: =DATEDIF(K37,TODAY(),"Y") -> 9 | M37: =VLOOKUP(B37,所有人!A:Q,7,FALSE) -> 信息化产品经理 | N37: 项目实施人员 | O37: 本科 | P37: 2016/08/01 | Q37: 9 | Z37: CNITSEC2019CISE04351 | AP37: 是 | AQ37: =COUNTA(T37:AN37) -> 3
A38: 37 | B38: 马栋 | C38: 男 | D38: AAAAAABBBBBB | E38: 139xxxxxxx | F38: =VLOOKUP(B38,所有人!A:Q,16,FALSE) -> 410328198907209538 | G38: =VLOOKUP(B38,所有人!A:Q,9,FALSE) -> 北京市 | I38: =VLOOKUP(B38,所有人!A:O,12,FALSE) -> 北京邮电大学 | J38: =VLOOKUP(B38,所有人!A:O,14,FALSE) -> 计算机与科学 | K38: =VLOOKUP(B38,所有人!A:Q,17,FALSE) -> 2020/07/22 | L38: =DATEDIF(K38,TODAY(),"Y") -> 5 | M38: =VLOOKUP(B38,所有人!A:Q,7,FALSE) -> 解决方案经理 | N38: 项目实施人员 | O38: 本科 | P38: 2012/04/19 | Q38: 14 | Z38: CNITSEC2022CISE13830 | AM38: PMP | AN38: 3668357 | AP38: 是 | AQ38: =COUNTA(T38:AN38) -> 4
A39: 38 | B39: 冯亚南 | C39: 男 | D39: AAAAAABBBBBB | E39: 139xxxxxxx | F39: =VLOOKUP(B39,所有人!A:Q,16,FALSE) -> 37292219890606609X | G39: =VLOOKUP(B39,所有人!A:Q,9,FALSE) -> 郑州市 | I39: =VLOOKUP(B39,所有人!A:O,12,FALSE) -> 中国管理软件学院 | J39: =VLOOKUP(B39,所有人!A:O,14,FALSE) -> 计算机控制及应用 | K39: =VLOOKUP(B39,所有人!A:Q,17,FALSE) -> 2012/01/05 | L39: =DATEDIF(K39,TODAY(),"Y") -> 14 | M39: =VLOOKUP(B39,所有人!A:Q,7,FALSE) -> 项目经理 | N39: 项目经理 | O39: 本科 | P39: 2010/10/14 | Q39: 15 | Z39: CNITSEC2019CISE04360 | AA39: 2021CSAWOM0242(R) | AM39: PMP | AN39: 1859399 | AP39: 是 | AQ39: =COUNTA(T39:AN39) -> 4
A40: 39 | B40: 马洪彬 | C40: 男 | D40: AAAAAABBBBBB | E40: 139xxxxxxx | F40: =VLOOKUP(B40,所有人!A:Q,16,FALSE) -> 222323197601110017 | G40: =VLOOKUP(B40,所有人!A:Q,9,FALSE) -> 大连市 | I40: =VLOOKUP(B40,所有人!A:O,12,FALSE) -> 兰州大学 | J40: =VLOOKUP(B40,所有人!A:O,14,FALSE) -> 科技信息专业 | K40: =VLOOKUP(B40,所有人!A:Q,17,FALSE) -> 2017/09/11 | L40: =DATEDIF(K40,TODAY(),"Y") -> 8 | M40: =VLOOKUP(B40,所有人!A:Q,7,FALSE) -> 组长 | N40: 项目实施人员 | O40: 本科 | P40: 2001/07/11 | Q40: 24 | Z40: CNITSEC2019CISE04336 | AP40: 是 | AQ40: =COUNTA(T40:AN40) -> 3
A41: 40 | B41: 姜福利 | C41: 男 | D41: AAAAAABBBBBB | E41: 139xxxxxxx | F41: =VLOOKUP(B41,所有人!A:Q,16,FALSE) -> 370281197812281819 | G41: =VLOOKUP(B41,所有人!A:Q,9,FALSE) -> 南京市 | I41: =VLOOKUP(B41,所有人!A:O,12,FALSE) -> 北京理工大学 | J41: =VLOOKUP(B41,所有人!A:O,14,FALSE) -> 计算机系统结构 | K41: =VLOOKUP(B41,所有人!A:Q,17,FALSE) -> 2015/03/31 | L41: =DATEDIF(K41,TODAY(),"Y") -> 11 | M41: =VLOOKUP(B41,所有人!A:Q,7,FALSE) -> 解决方案经理 | N41: 架构师 | O41: 硕士研究生 | P41: 2001/08/01 | Q41: 24 | Z41: CNITSEC2023CISP DSG25254 | AP41: 是 | AQ41: =COUNTA(T41:AN41) -> 3
A42: 41 | B42: 祁海 | C42: 男 | D42: AAAAAABBBBBB | E42: 139xxxxxxx | F42: =VLOOKUP(B42,所有人!A:Q,16,FALSE) -> 320923198703240030 | G42: =VLOOKUP(B42,所有人!A:Q,9,FALSE) -> 南京市 | I42: =VLOOKUP(B42,所有人!A:O,12,FALSE) -> 常熟理工学院 | J42: =VLOOKUP(B42,所有人!A:O,14,FALSE) -> 网络工程 | K42: =VLOOKUP(B42,所有人!A:Q,17,FALSE) -> 2012/04/26 | L42: =DATEDIF(K42,TODAY(),"Y") -> 14 | M42: =VLOOKUP(B42,所有人!A:Q,7,FALSE) -> 系统运营经理 | N42: 项目实施人员 | O42: 本科 | P42: 2012/04/26 | Q42: 14 | Z42: CNITSEC2022CIS001814 | AP42: 是 | AQ42: =COUNTA(T42:AN42) -> 3
A43: 42 | B43: 李宁辉 | C43: 男 | D43: AAAAAABBBBBB | E43: 139xxxxxxx | F43: =VLOOKUP(B43,所有人!A:Q,16,FALSE) -> 412702199408283156 | G43: =VLOOKUP(B43,所有人!A:Q,9,FALSE) -> 福州市 | I43: =VLOOKUP(B43,所有人!A:O,12,FALSE) -> 兰州交通大学 | J43: =VLOOKUP(B43,所有人!A:O,14,FALSE) -> 计算机技术 | K43: =VLOOKUP(B43,所有人!A:Q,17,FALSE) -> 2023/04/17 | L43: =DATEDIF(K43,TODAY(),"Y") -> 3 | M43: =VLOOKUP(B43,所有人!A:Q,7,FALSE) -> 解决方案经理 | N43: 测试人员 | O43: 硕士研究生 | P43: 2020/07/20 | Q43: 5 | AM43: PMP | AN43: 3489312 | AP43: 是 | AQ43: =COUNTA(T43:AN43) -> 3
A44: 43 | B44: 李智 | C44: 男 | D44: AAAAAABBBBBB | E44: 139xxxxxxx | F44: =VLOOKUP(B44,所有人!A:Q,16,FALSE) -> 140402198004223212 | G44: =VLOOKUP(B44,所有人!A:Q,9,FALSE) -> 北京市 | I44: =VLOOKUP(B44,所有人!A:O,12,FALSE) -> 北京林业大学 | J44: =VLOOKUP(B44,所有人!A:O,14,FALSE) -> 计算机科技与技术 | K44: =VLOOKUP(B44,所有人!A:Q,17,FALSE) -> 2020/06/28 | L44: =DATEDIF(K44,TODAY(),"Y") -> 6 | M44: =VLOOKUP(B44,所有人!A:Q,7,FALSE) -> 解决方案经理 | N44: 项目实施人员 | O44: 本科 | P44: 2000/07/01 | Q44: 25 | AM44: 系统集成项目管理工程师 | AN44: 14143110047 | AP44: 是 | AQ44: =COUNTA(T44:AN44) -> 2
A45: 44 | B45: 王亚辉 | C45: 男 | D45: AAAAAABBBBBB | E45: 139xxxxxxx | F45: =VLOOKUP(B45,所有人!A:Q,16,FALSE) -> 411526198908232915 | G45: =VLOOKUP(B45,所有人!A:Q,9,FALSE) -> 武汉市 | I45: =VLOOKUP(B45,所有人!A:O,12,FALSE) -> 黄河科技学院 | J45: =VLOOKUP(B45,所有人!A:O,14,FALSE) -> 计算机科学与技术 | K45: =VLOOKUP(B45,所有人!A:Q,17,FALSE) -> 2015/11/05 | L45: =DATEDIF(K45,TODAY(),"Y") -> 10 | M45: =VLOOKUP(B45,所有人!A:Q,7,FALSE) -> Java工程师 | N45: 项目实施人员 | O45: 本科 | P45: 2012/11/05 | Q45: 13 | AM45: 软件设计师 | AN45: 11215410151 | AP45: 是 | AQ45: =COUNTA(T45:AN45) -> 6
A46: 45 | B46: 白首骏 | C46: 男 | D46: AAAAAABBBBBB | E46: 139xxxxxxx | F46: =VLOOKUP(B46,所有人!A:Q,16,FALSE) -> 110101199010304031 | G46: =VLOOKUP(B46,所有人!A:Q,9,FALSE) -> 北京市 | I46: =VLOOKUP(B46,所有人!A:O,12,FALSE) -> 北京城市学院 | J46: =VLOOKUP(B46,所有人!A:O,14,FALSE) -> 计算机科学与技术 | K46: =VLOOKUP(B46,所有人!A:Q,17,FALSE) -> 2020/03/25 | L46: =DATEDIF(K46,TODAY(),"Y") -> 6 | M46: =VLOOKUP(B46,所有人!A:Q,7,FALSE) -> Java工程师 | N46: 项目实施人员 | O46: 本科 | P46: 2013/06/24 | Q46: 12 | AP46: 是 | AQ46: =COUNTA(T46:AN46) -> 0
A47: 46 | B47: 班宏 | C47: 男 | D47: AAAAAABBBBBB | E47: 139xxxxxxx | F47: =VLOOKUP(B47,所有人!A:Q,16,FALSE) -> 452727199810310014 | G47: =VLOOKUP(B47,所有人!A:Q,9,FALSE) -> 南宁市 | I47: =VLOOKUP(B47,所有人!A:O,12,FALSE) -> 广西民族师范学院 | J47: =VLOOKUP(B47,所有人!A:O,14,FALSE) -> 网络工程 | K47: =VLOOKUP(B47,所有人!A:Q,17,FALSE) -> 2021/05/14 | L47: =DATEDIF(K47,TODAY(),"Y") -> 5 | M47: =VLOOKUP(B47,所有人!A:Q,7,FALSE) -> 系统运营经理 | N47: 项目实施人员 | O47: 本科 | P47: 2020/08/01 | Q47: 5 | AP47: 是 | AQ47: =COUNTA(T47:AN47) -> 0
A48: 47 | B48: 卜凡成1 | C48: 男 | D48: AAAAAABBBBBB | E48: 139xxxxxxx | F48: =VLOOKUP(B48,所有人!A:Q,16,FALSE) -> 371102199402017512 | G48: =VLOOKUP(B48,所有人!A:Q,9,FALSE) -> 济南市 | I48: =VLOOKUP(B48,所有人!A:O,12,FALSE) -> 山东理工大学 | J48: =VLOOKUP(B48,所有人!A:O,14,FALSE) -> 电子信息科学与技术 | K48: =VLOOKUP(B48,所有人!A:Q,17,FALSE) -> 2021/06/01 | L48: =DATEDIF(K48,TODAY(),"Y") -> 5 | M48: =VLOOKUP(B48,所有人!A:Q,7,FALSE) -> Java工程师 | N48: 项目实施人员 | O48: 本科 | P48: 2016/07/01 | Q48: 9 | AP48: 是 | AQ48: =COUNTA(T48:AN48) -> 0
A49: 48 | B49: 步学剑 | C49: 男 | D49: AAAAAABBBBBB | E49: 139xxxxxxx | F49: =VLOOKUP(B49,所有人!A:Q,16,FALSE) -> 120222199208243616 | G49: =VLOOKUP(B49,所有人!A:Q,9,FALSE) -> 天津市 | I49: =VLOOKUP(B49,所有人!A:O,12,FALSE) -> 湖南农业大学 | J49: =VLOOKUP(B49,所有人!A:O,14,FALSE) -> 食品科学与工程 | K49: =VLOOKUP(B49,所有人!A:Q,17,FALSE) -> 2023/04/12 | L49: =DATEDIF(K49,TODAY(),"Y") -> 3 | M49: =VLOOKUP(B49,所有人!A:Q,7,FALSE) -> Java工程师 | N49: 架构师 | O49: 本科 | P49: 2015/10/10 | Q49: 10 | AP49: 是 | AQ49: =COUNTA(T49:AN49) -> 0
A50: 49 | B50: 蔡小龙 | C50: 男 | D50: AAAAAABBBBBB | E50: 139xxxxxxx | F50: =VLOOKUP(B50,所有人!A:Q,16,FALSE) -> 640302198908300711 | G50: =VLOOKUP(B50,所有人!A:Q,9,FALSE) -> 银川市 | I50: =VLOOKUP(B50,所有人!A:O,12,FALSE) -> 北京邮电大学 | J50: =VLOOKUP(B50,所有人!A:O,14,FALSE) -> 电子信息工程 | K50: =VLOOKUP(B50,所有人!A:Q,17,FALSE) -> 2023/02/06 | L50: =DATEDIF(K50,TODAY(),"Y") -> 3 | M50: =VLOOKUP(B50,所有人!A:Q,7,FALSE) -> 跨专业支持工程师 | N50: 项目实施人员 | O50: 本科 | P50: 2011/07/12 | Q50: 14 | AP50: 是 | AQ50: =COUNTA(T50:AN50) -> 0
A51: 50 | B51: 藏润强 | C51: 男 | D51: AAAAAABBBBBB | E51: 139xxxxxxx | F51: =VLOOKUP(B51,所有人!A:Q,16,FALSE) -> 230828199012107416 | G51: =VLOOKUP(B51,所有人!A:Q,9,FALSE) -> 北京市 | I51: =VLOOKUP(B51,所有人!A:O,12,FALSE) -> 中国人民大学 | J51: =VLOOKUP(B51,所有人!A:O,14,FALSE) -> 计算机应用技术 | K51: =VLOOKUP(B51,所有人!A:Q,17,FALSE) -> 2024/07/01 | L51: =DATEDIF(K51,TODAY(),"Y") -> 1 | M51: =VLOOKUP(B51,所有人!A:Q,7,FALSE) -> AI算法工程师 | N51: 项目实施人员 | O51: 博士研究生 | P51: 2024/07/01 | Q51: 1 | AP51: 是 | AQ51: =COUNTA(T51:AN51) -> 0
A52: 51 | B52: 曹洋 | C52: 男 | D52: AAAAAABBBBBB | E52: 139xxxxxxx | F52: =VLOOKUP(B52,所有人!A:Q,16,FALSE) -> 37012519960615001X | G52: =VLOOKUP(B52,所有人!A:Q,9,FALSE) -> 长春市 | I52: =VLOOKUP(B52,所有人!A:O,12,FALSE) -> 黑龙江八一农垦大学 | J52: =VLOOKUP(B52,所有人!A:O,14,FALSE) -> 通信工程 | K52: =VLOOKUP(B52,所有人!A:Q,17,FALSE) -> 2022/09/20 | L52: =DATEDIF(K52,TODAY(),"Y") -> 3 | M52: =VLOOKUP(B52,所有人!A:Q,7,FALSE) -> 系统运营经理 | N52: 测试人员 | O52: 本科 | P52: 2019/07/01 | Q52: 6 | AP52: 是 | AQ52: =COUNTA(T52:AN52) -> 0
A53: 52 | B53: 岑俊杰 | C53: 男 | D53: AAAAAABBBBBB | E53: 139xxxxxxx | F53: =VLOOKUP(B53,所有人!A:Q,16,FALSE) -> 511133199907140613 | G53: =VLOOKUP(B53,所有人!A:Q,9,FALSE) -> 南京市 | I53: =VLOOKUP(B53,所有人!A:O,12,FALSE) -> 浙江万里学院 | J53: =VLOOKUP(B53,所有人!A:O,14,FALSE) -> 金融工程 | K53: =VLOOKUP(B53,所有人!A:Q,17,FALSE) -> 2025/08/01 | L53: =DATEDIF(K53,TODAY(),"Y") -> 0 | M53: =VLOOKUP(B53,所有人!A:Q,7,FALSE) -> 大数据工程师 | N53: 项目实施人员 | O53: 本科 | P53: 2021/12/21 | Q53: 4 | AP53: 是 | AQ53: =COUNTA(T53:AN53) -> 0
A54: 53 | B54: 柴伟 | C54: 男 | D54: AAAAAABBBBBB | E54: 139xxxxxxx | F54: =VLOOKUP(B54,所有人!A:Q,16,FALSE) -> 152827198109240011 | G54: =VLOOKUP(B54,所有人!A:Q,9,FALSE) -> 呼和浩特市 | I54: =VLOOKUP(B54,所有人!A:O,12,FALSE) -> 内蒙古工业大学 | J54: =VLOOKUP(B54,所有人!A:O,14,FALSE) -> 通信工程 | K54: =VLOOKUP(B54,所有人!A:Q,17,FALSE) -> 2021/02/18 | L54: =DATEDIF(K54,TODAY(),"Y") -> 5 | M54: =VLOOKUP(B54,所有人!A:Q,7,FALSE) -> 系统运营经理 | N54: 项目实施人员 | O54: 本科 | P54: 2006/03/08 | Q54: 20 | AP54: 是 | AQ54: =COUNTA(T54:AN54) -> 0
A55: 54 | B55: 陈苍山 | C55: 男 | D55: AAAAAABBBBBB | E55: 139xxxxxxx | F55: =VLOOKUP(B55,所有人!A:Q,16,FALSE) -> 350301199008060715 | G55: =VLOOKUP(B55,所有人!A:Q,9,FALSE) -> 北京市 | I55: =VLOOKUP(B55,所有人!A:O,12,FALSE) -> 福建师范大学 | J55: =VLOOKUP(B55,所有人!A:O,14,FALSE) -> 光信息科学与技术 | K55: =VLOOKUP(B55,所有人!A:Q,17,FALSE) -> 2024/04/07 | L55: =DATEDIF(K55,TODAY(),"Y") -> 2 | M55: =VLOOKUP(B55,所有人!A:Q,7,FALSE) -> 前端工程师 | N55: 测试人员 | O55: 本科 | P55: 2014/08/01 | Q55: 11 | AP55: 是 | AQ55: =COUNTA(T55:AN55) -> 0
A56: 55 | B56: 陈钊2 | C56: 男 | D56: AAAAAABBBBBB | E56: 139xxxxxxx | F56: =VLOOKUP(B56,所有人!A:Q,16,FALSE) -> 372328199306030333 | G56: =VLOOKUP(B56,所有人!A:Q,9,FALSE) -> 济南市 | I56: =VLOOKUP(B56,所有人!A:O,12,FALSE) -> 山东工商学院 | J56: =VLOOKUP(B56,所有人!A:O,14,FALSE) -> 计算机科学与技术 | K56: =VLOOKUP(B56,所有人!A:Q,17,FALSE) -> 2021/07/05 | L56: =DATEDIF(K56,TODAY(),"Y") -> 4 | M56: =VLOOKUP(B56,所有人!A:Q,7,FALSE) -> Java工程师 | N56: 项目实施人员 | O56: 本科 | P56: 2017/03/20 | Q56: 9 | AP56: 是 | AQ56: =COUNTA(T56:AN56) -> 0
A57: 56 | B57: 陈振 | C57: 男 | D57: AAAAAABBBBBB | E57: 139xxxxxxx | F57: =VLOOKUP(B57,所有人!A:Q,16,FALSE) -> 411481198507199017 | G57: =VLOOKUP(B57,所有人!A:Q,9,FALSE) -> 广州市 | I57: =VLOOKUP(B57,所有人!A:O,12,FALSE) -> 河南理工大学 | J57: =VLOOKUP(B57,所有人!A:O,14,FALSE) -> 计算机科学与技术 | K57: =VLOOKUP(B57,所有人!A:Q,17,FALSE) -> 2018/07/24 | L57: =DATEDIF(K57,TODAY(),"Y") -> 7 | M57: =VLOOKUP(B57,所有人!A:Q,7,FALSE) -> 大数据工程师 | N57: 项目实施人员 | O57: 本科 | P57: 2009/09/21 | Q57: 16 | Z57: CNITSEC2019CISE04348 | AP57: 是 | AQ57: =COUNTA(T57:AN57) -> 1
A58: 57 | B58: 仇红建1 | C58: 男 | D58: AAAAAABBBBBB | E58: 139xxxxxxx | F58: =VLOOKUP(B58,所有人!A:Q,16,FALSE) -> 120225198801053316 | G58: =VLOOKUP(B58,所有人!A:Q,9,FALSE) -> 天津市 | I58: =VLOOKUP(B58,所有人!A:O,12,FALSE) -> 天津理工大学 | J58: =VLOOKUP(B58,所有人!A:O,14,FALSE) -> 光信息科学与技术 | K58: =VLOOKUP(B58,所有人!A:Q,17,FALSE) -> 2022/07/28 | L58: =DATEDIF(K58,TODAY(),"Y") -> 3 | M58: =VLOOKUP(B58,所有人!A:Q,7,FALSE) -> 跨专业支持工程师 | N58: 项目实施人员 | O58: 本科 | P58: 2010/06/23 | Q58: 15 | Z58: CNITSEC2019CISE04365 | AP58: 是 | AQ58: =COUNTA(T58:AN58) -> 1
A59: 58 | B59: 从继通 | C59: 男 | D59: AAAAAABBBBBB | E59: 139xxxxxxx | F59: =VLOOKUP(B59,所有人!A:Q,16,FALSE) -> 12010119851015353X | G59: =VLOOKUP(B59,所有人!A:Q,9,FALSE) -> 天津市 | I59: =VLOOKUP(B59,所有人!A:O,12,FALSE) -> 大连民族学院 | J59: =VLOOKUP(B59,所有人!A:O,14,FALSE) -> 软件工程 | K59: =VLOOKUP(B59,所有人!A:Q,17,FALSE) -> 2019/05/08 | L59: =DATEDIF(K59,TODAY(),"Y") -> 7 | M59: =VLOOKUP(B59,所有人!A:Q,7,FALSE) -> Java工程师 | N59: 测试人员 | O59: 本科 | P59: 2008/07/07 | Q59: 17 | AP59: 是 | AQ59: =COUNTA(T59:AN59) -> 0
A60: 59 | B60: 崔澎 | C60: 男 | D60: AAAAAABBBBBB | E60: 139xxxxxxx | F60: =VLOOKUP(B60,所有人!A:Q,16,FALSE) -> 370102197103070815 | G60: =VLOOKUP(B60,所有人!A:Q,9,FALSE) -> 北京市 | I60: =VLOOKUP(B60,所有人!A:O,12,FALSE) -> 北京信息科技大学 | J60: =VLOOKUP(B60,所有人!A:O,14,FALSE) -> 精密仪器 | K60: =VLOOKUP(B60,所有人!A:Q,17,FALSE) -> 2020/09/24 | L60: =DATEDIF(K60,TODAY(),"Y") -> 5 | M60: =VLOOKUP(B60,所有人!A:Q,7,FALSE) -> 项目经理 | N60: 项目实施人员 | O60: 本科 | P60: 1994/08/01 | Q60: 31 | AP60: 是 | AQ60: =COUNTA(T60:AN60) -> 0
A61: 60 | B61: 代城 | C61: 男 | D61: AAAAAABBBBBB | E61: 139xxxxxxx | F61: =VLOOKUP(B61,所有人!A:Q,16,FALSE) -> 511023199009153676 | G61: =VLOOKUP(B61,所有人!A:Q,9,FALSE) -> 福州市 | I61: =VLOOKUP(B61,所有人!A:O,12,FALSE) -> 江西理工大学应用科学学院 | J61: =VLOOKUP(B61,所有人!A:O,14,FALSE) -> 信息与计算科学 | K61: =VLOOKUP(B61,所有人!A:Q,17,FALSE) -> 2025/10/20 | L61: =DATEDIF(K61,TODAY(),"Y") -> 0 | M61: =VLOOKUP(B61,所有人!A:Q,7,FALSE) -> 大数据工程师 | N61: 项目实施人员 | O61: 本科 | P61: 2014/07/01 | Q61: 11 | AP61: 是 | AQ61: =COUNTA(T61:AN61) -> 0
A62: 61 | B62: 邓超 | C62: 男 | D62: AAAAAABBBBBB | E62: 139xxxxxxx | F62: =VLOOKUP(B62,所有人!A:Q,16,FALSE) -> 42900419880925491X | G62: =VLOOKUP(B62,所有人!A:Q,9,FALSE) -> 武汉市 | I62: =VLOOKUP(B62,所有人!A:O,12,FALSE) -> 武汉理工大学 | J62: =VLOOKUP(B62,所有人!A:O,14,FALSE) -> 计算机科学与技术 | K62: =VLOOKUP(B62,所有人!A:Q,17,FALSE) -> 2022/03/01 | L62: =DATEDIF(K62,TODAY(),"Y") -> 4 | M62: =VLOOKUP(B62,所有人!A:Q,7,FALSE) -> 资深C语言工程师 | N62: 项目实施人员 | O62: 本科 | P62: 2010/03/01 | Q62: 16 | AP62: 是 | AQ62: =COUNTA(T62:AN62) -> 0
A63: 62 | B63: 邓怀俊 | C63: 男 | D63: AAAAAABBBBBB | E63: 139xxxxxxx | F63: =VLOOKUP(B63,所有人!A:Q,16,FALSE) -> 413026199012169318 | G63: =VLOOKUP(B63,所有人!A:Q,9,FALSE) -> 北京市 | I63: =VLOOKUP(B63,所有人!A:O,12,FALSE) -> 新乡医学院三全学院 | J63: =VLOOKUP(B63,所有人!A:O,14,FALSE) -> 生物医学工程 | K63: =VLOOKUP(B63,所有人!A:Q,17,FALSE) -> 2021/05/19 | L63: =DATEDIF(K63,TODAY(),"Y") -> 5 | M63: =VLOOKUP(B63,所有人!A:Q,7,FALSE) -> Java工程师 | N63: 测试人员 | O63: 本科 | P63: 2014/07/01 | Q63: 11 | AP63: 是 | AQ63: =COUNTA(T63:AN63) -> 0
A64: 63 | B64: 邓辉 | C64: 男 | D64: AAAAAABBBBBB | E64: 139xxxxxxx | F64: =VLOOKUP(B64,所有人!A:Q,16,FALSE) -> 450512199310110035 | G64: =VLOOKUP(B64,所有人!A:Q,9,FALSE) -> 南宁市 | I64: =VLOOKUP(B64,所有人!A:O,12,FALSE) -> 桂林电子科技大学 | J64: =VLOOKUP(B64,所有人!A:O,14,FALSE) -> 信息与计算科学 | K64: =VLOOKUP(B64,所有人!A:Q,17,FALSE) -> 2024/11/04 | L64: =DATEDIF(K64,TODAY(),"Y") -> 1 | M64: =VLOOKUP(B64,所有人!A:Q,7,FALSE) -> 系统运营经理 | N64: 项目实施人员 | O64: 本科 | P64: 2015/07/13 | Q64: 10 | AP64: 是 | AQ64: =COUNTA(T64:AN64) -> 0
A65: 64 | B65: 邓尚举 | C65: 男 | D65: AAAAAABBBBBB | E65: 139xxxxxxx | F65: =VLOOKUP(B65,所有人!A:Q,16,FALSE) -> 522121199401181212 | G65: =VLOOKUP(B65,所有人!A:Q,9,FALSE) -> 贵阳市 | I65: =VLOOKUP(B65,所有人!A:O,12,FALSE) -> 新疆大学 | J65: =VLOOKUP(B65,所有人!A:O,14,FALSE) -> 信息与通信工程 | K65: =VLOOKUP(B65,所有人!A:Q,17,FALSE) -> 2022/07/04 | L65: =DATEDIF(K65,TODAY(),"Y") -> 3 | M65: =VLOOKUP(B65,所有人!A:Q,7,FALSE) -> Python工程师 | N65: 项目实施人员 | O65: 硕士研究生 | P65: 2022/07/04 | Q65: 3 | AP65: 是 | AQ65: =COUNTA(T65:AN65) -> 0
A66: 65 | B66: 丁凯云 | C66: 男 | D66: AAAAAABBBBBB | E66: 139xxxxxxx | F66: =VLOOKUP(B66,所有人!A:Q,16,FALSE) -> 410521200112134524 | G66: =VLOOKUP(B66,所有人!A:Q,9,FALSE) -> 北京市 | I66: =VLOOKUP(B66,所有人!A:O,12,FALSE) -> 晋中信息学院 | J66: =VLOOKUP(B66,所有人!A:O,14,FALSE) -> 网络工程 | K66: =VLOOKUP(B66,所有人!A:Q,17,FALSE) -> 2025/07/01 | L66: =DATEDIF(K66,TODAY(),"Y") -> 0 | M66: =VLOOKUP(B66,所有人!A:Q,7,FALSE) -> 测试工程师 | N66: 项目实施人员 | O66: 本科 | P66: 2025/07/01 | Q66: 0 | AP66: 是 | AQ66: =COUNTA(T66:AN66) -> 0
A67: 66 | B67: 丁慎炳 | C67: 男 | D67: AAAAAABBBBBB | E67: 139xxxxxxx | F67: =VLOOKUP(B67,所有人!A:Q,16,FALSE) -> 370304200011014718 | G67: =VLOOKUP(B67,所有人!A:Q,9,FALSE) -> 济南市 | I67: =VLOOKUP(B67,所有人!A:O,12,FALSE) -> 齐鲁师范学院 | J67: =VLOOKUP(B67,所有人!A:O,14,FALSE) -> 计算机科学与技术 | K67: =VLOOKUP(B67,所有人!A:Q,17,FALSE) -> 2023/07/03 | L67: =DATEDIF(K67,TODAY(),"Y") -> 2 | M67: =VLOOKUP(B67,所有人!A:Q,7,FALSE) -> 系统运营专家 | N67: 测试人员 | O67: 本科 | P67: 2023/06/12 | Q67: 2 | AP67: 是 | AQ67: =COUNTA(T67:AN67) -> 0
A68: 67 | B68: 窦晶 | C68: 男 | D68: AAAAAABBBBBB | E68: 139xxxxxxx | F68: =VLOOKUP(B68,所有人!A:Q,16,FALSE) -> 22038119830210764X | G68: =VLOOKUP(B68,所有人!A:Q,9,FALSE) -> 大连市 | I68: =VLOOKUP(B68,所有人!A:O,12,FALSE) -> 大连理工大学 | J68: =VLOOKUP(B68,所有人!A:O,14,FALSE) -> 计算数学 | K68: =VLOOKUP(B68,所有人!A:Q,17,FALSE) -> 2017/09/01 | L68: =DATEDIF(K68,TODAY(),"Y") -> 8 | M68: =VLOOKUP(B68,所有人!A:Q,7,FALSE) -> C语言工程师/信令工程师 | N68: 项目实施人员 | O68: 硕士研究生 | P68: 2007/07/10 | Q68: 18 | Z68: CNITSEC2019CISE04338 | AP68: 是 | AQ68: =COUNTA(T68:AN68) -> 1
A69: 68 | B69: 段淇 | C69: 男 | D69: AAAAAABBBBBB | E69: 139xxxxxxx | F69: =VLOOKUP(B69,所有人!A:Q,16,FALSE) -> 231003200004281014 | G69: =VLOOKUP(B69,所有人!A:Q,9,FALSE) -> 北京市 | I69: =VLOOKUP(B69,所有人!A:O,12,FALSE) -> 大庆师范学院 | J69: =VLOOKUP(B69,所有人!A:O,14,FALSE) -> 网络工程 | K69: =VLOOKUP(B69,所有人!A:Q,17,FALSE) -> 2023/01/16 | L69: =DATEDIF(K69,TODAY(),"Y") -> 3 | M69: =VLOOKUP(B69,所有人!A:Q,7,FALSE) -> 前端工程师 | N69: 项目实施人员 | O69: 本科 | P69: 2022/06/14 | Q69: 3 | AP69: 是 | AQ69: =COUNTA(T69:AN69) -> 0
A70: 69 | B70: 凡同飞 | C70: 男 | D70: AAAAAABBBBBB | E70: 139xxxxxxx | F70: =VLOOKUP(B70,所有人!A:Q,16,FALSE) -> 530381198410302939 | G70: =VLOOKUP(B70,所有人!A:Q,9,FALSE) -> 昆明市 | I70: =VLOOKUP(B70,所有人!A:O,12,FALSE) -> 云南财经大学 | J70: =VLOOKUP(B70,所有人!A:O,14,FALSE) -> 计算机科学与技术 | K70: =VLOOKUP(B70,所有人!A:Q,17,FALSE) -> 2013/03/01 | L70: =DATEDIF(K70,TODAY(),"Y") -> 13 | M70: =VLOOKUP(B70,所有人!A:Q,7,FALSE) -> 实施运维工程师 | N70: 项目实施人员 | O70: 本科 | P70: 2009/07/01 | Q70: 16 | AP70: 是 | AQ70: =COUNTA(T70:AN70) -> 0
A71: 70 | B71: 樊昕宇 | C71: 男 | D71: AAAAAABBBBBB | E71: 139xxxxxxx | F71: =VLOOKUP(B71,所有人!A:Q,16,FALSE) -> 420922199406282332 | G71: =VLOOKUP(B71,所有人!A:Q,9,FALSE) -> 武汉市 | I71: =VLOOKUP(B71,所有人!A:O,12,FALSE) -> 湖北工程学院新技术学院 | J71: =VLOOKUP(B71,所有人!A:O,14,FALSE) -> 计算机科学与技术 | K71: =VLOOKUP(B71,所有人!A:Q,17,FALSE) -> 2025/08/11 | L71: =DATEDIF(K71,TODAY(),"Y") -> 0 | M71: =VLOOKUP(B71,所有人!A:Q,7,FALSE) -> 产品设计专家 | N71: 测试人员 | O71: 本科 | P71: 2016/07/25 | Q71: 9 | AP71: 是 | AQ71: =COUNTA(T71:AN71) -> 0
A72: 71 | B72: 范国征 | C72: 男 | D72: AAAAAABBBBBB | E72: 139xxxxxxx | F72: =VLOOKUP(B72,所有人!A:Q,16,FALSE) -> 411081198811054590 | G72: =VLOOKUP(B72,所有人!A:Q,9,FALSE) -> 郑州市 | I72: =VLOOKUP(B72,所有人!A:O,12,FALSE) -> 河南中医药大学 | J72: =VLOOKUP(B72,所有人!A:O,14,FALSE) -> 计算机科学与技术 | K72: =VLOOKUP(B72,所有人!A:Q,17,FALSE) -> 2023/05/22 | L72: =DATEDIF(K72,TODAY(),"Y") -> 3 | M72: =VLOOKUP(B72,所有人!A:Q,7,FALSE) -> 跨专业支持工程师 | N72: 项目实施人员 | O72: 本科 | P72: 2015/08/01 | Q72: 10 | Z72: CNITSEC2019CISO07265 | AP72: 是 | AQ72: =COUNTA(T72:AN72) -> 1
A73: 72 | B73: 葛大龙 | C73: 男 | D73: AAAAAABBBBBB | E73: 139xxxxxxx | F73: =VLOOKUP(B73,所有人!A:Q,16,FALSE) -> 410426198910014056 | G73: =VLOOKUP(B73,所有人!A:Q,9,FALSE) -> 北京市 | I73: =VLOOKUP(B73,所有人!A:O,12,FALSE) -> 河南理工大学 | J73: =VLOOKUP(B73,所有人!A:O,14,FALSE) -> 化学工程与工艺 | K73: =VLOOKUP(B73,所有人!A:Q,17,FALSE) -> 2021/06/22 | L73: =DATEDIF(K73,TODAY(),"Y") -> 5 | M73: =VLOOKUP(B73,所有人!A:Q,7,FALSE) -> Java工程师 | N73: 项目实施人员 | O73: 本科 | P73: 2011/07/01 | Q73: 14 | AP73: 是 | AQ73: =COUNTA(T73:AN73) -> 0
A74: 73 | B74: 龚霞 | C74: 男 | D74: AAAAAABBBBBB | E74: 139xxxxxxx | F74: =VLOOKUP(B74,所有人!A:Q,16,FALSE) -> 500231199008141022 | G74: =VLOOKUP(B74,所有人!A:Q,9,FALSE) -> 重庆市 | I74: =VLOOKUP(B74,所有人!A:O,12,FALSE) -> 重庆工商大学 | J74: =VLOOKUP(B74,所有人!A:O,14,FALSE) -> 计算机科学与技术 | K74: =VLOOKUP(B74,所有人!A:Q,17,FALSE) -> 2017/08/07 | L74: =DATEDIF(K74,TODAY(),"Y") -> 8 | M74: =VLOOKUP(B74,所有人!A:Q,7,FALSE) -> 系统运营经理 | N74: 项目实施人员 | O74: 本科 | P74: 2012/07/01 | Q74: 13 | AP74: 是 | AQ74: =COUNTA(T74:AN74) -> 0
A75: 74 | B75: 谷云鹤 | C75: 男 | D75: AAAAAABBBBBB | E75: 139xxxxxxx | F75: =VLOOKUP(B75,所有人!A:Q,16,FALSE) -> 130531198703061414 | G75: =VLOOKUP(B75,所有人!A:Q,9,FALSE) -> 天津市 | I75: =VLOOKUP(B75,所有人!A:O,12,FALSE) -> 河北科技师范学院 | J75: =VLOOKUP(B75,所有人!A:O,14,FALSE) -> 园林 | K75: =VLOOKUP(B75,所有人!A:Q,17,FALSE) -> 2017/03/02 | L75: =DATEDIF(K75,TODAY(),"Y") -> 9 | M75: =VLOOKUP(B75,所有人!A:Q,7,FALSE) -> Java工程师 | N75: 项目实施人员 | O75: 本科 | P75: 2013/07/01 | Q75: 12 | AP75: 是 | AQ75: =COUNTA(T75:AN75) -> 0
A76: 75 | B76: 顾星宇 | C76: 男 | D76: AAAAAABBBBBB | E76: 139xxxxxxx | F76: =VLOOKUP(B76,所有人!A:Q,16,FALSE) -> 320682199910184674 | G76: =VLOOKUP(B76,所有人!A:Q,9,FALSE) -> 南京市 | I76: =VLOOKUP(B76,所有人!A:O,12,FALSE) -> 金陵科技学院 | J76: =VLOOKUP(B76,所有人!A:O,14,FALSE) -> 信息安全 | K76: =VLOOKUP(B76,所有人!A:Q,17,FALSE) -> 2021/07/01 | L76: =DATEDIF(K76,TODAY(),"Y") -> 4 | M76: =VLOOKUP(B76,所有人!A:Q,7,FALSE) -> 系统运营经理 | N76: 项目实施人员 | O76: 本科 | P76: 2020/11/09 | Q76: 5 | Z76: CNITSEC2023CISE06720 | AP76: 是 | AQ76: =COUNTA(T76:AN76) -> 1
A77: 76 | B77: 胡凤 | C77: 男 | D77: AAAAAABBBBBB | E77: 139xxxxxxx | F77: =VLOOKUP(B77,所有人!A:Q,16,FALSE) -> 511621199603177902 | G77: =VLOOKUP(B77,所有人!A:Q,9,FALSE) -> 重庆市 | I77: =VLOOKUP(B77,所有人!A:O,12,FALSE) -> 重庆工程学院 | J77: =VLOOKUP(B77,所有人!A:O,14,FALSE) -> 网络工程 | K77: =VLOOKUP(B77,所有人!A:Q,17,FALSE) -> 2021/01/15 | L77: =DATEDIF(K77,TODAY(),"Y") -> 5 | M77: =VLOOKUP(B77,所有人!A:Q,7,FALSE) -> 系统运营经理 | N77: 项目实施人员 | O77: 本科 | P77: 2019/07/13 | Q77: 6 | Z77: CNITSEC2021CISE20458 | AP77: 是 | AQ77: =COUNTA(T77:AN77) -> 1
A78: 77 | B78: 黄晋健 | C78: 男 | D78: AAAAAABBBBBB | E78: 139xxxxxxx | F78: =VLOOKUP(B78,所有人!A:Q,16,FALSE) -> 440181199802241815 | G78: =VLOOKUP(B78,所有人!A:Q,9,FALSE) -> 广州市 | I78: =VLOOKUP(B78,所有人!A:O,12,FALSE) -> 广东第二师范学院 | J78: =VLOOKUP(B78,所有人!A:O,14,FALSE) -> 网络工程 | K78: =VLOOKUP(B78,所有人!A:Q,17,FALSE) -> 2020/07/01 | L78: =DATEDIF(K78,TODAY(),"Y") -> 5 | M78: =VLOOKUP(B78,所有人!A:Q,7,FALSE) -> 系统可靠性监测专家 | N78: 项目实施人员 | O78: 本科 | P78: 2019/07/22 | Q78: 6 | Z78: CNITSEC2023CISO11934 | AP78: 是 | AQ78: =COUNTA(T78:AN78) -> 1
A79: 78 | B79: 黄晶 | C79: 男 | D79: AAAAAABBBBBB | E79: 139xxxxxxx | F79: =VLOOKUP(B79,所有人!A:Q,16,FALSE) -> 51303019800515201X | G79: =VLOOKUP(B79,所有人!A:Q,9,FALSE) -> 南宁市 | I79: =VLOOKUP(B79,所有人!A:O,12,FALSE) -> 中国科学技术大学 | J79: =VLOOKUP(B79,所有人!A:O,14,FALSE) -> 光学 | K79: =VLOOKUP(B79,所有人!A:Q,17,FALSE) -> 2021/06/24 | L79: =DATEDIF(K79,TODAY(),"Y") -> 5 | M79: =VLOOKUP(B79,所有人!A:Q,7,FALSE) -> 解决方案经理 | N79: 项目实施人员 | O79: 硕士研究生 | P79: 2005/07/01 | Q79: 20 | AP79: 是 | AQ79: =COUNTA(T79:AN79) -> 0
A80: 79 | B80: 黄山山 | C80: 男 | D80: AAAAAABBBBBB | E80: 139xxxxxxx | F80: =VLOOKUP(B80,所有人!A:Q,16,FALSE) -> 110223199804117573 | G80: =VLOOKUP(B80,所有人!A:Q,9,FALSE) -> 北京市 | I80: =VLOOKUP(B80,所有人!A:O,12,FALSE) -> 北京联合大学 | J80: =VLOOKUP(B80,所有人!A:O,14,FALSE) -> 信息管理与信息系统 | K80: =VLOOKUP(B80,所有人!A:Q,17,FALSE) -> 2020/07/09 | L80: =DATEDIF(K80,TODAY(),"Y") -> 5 | M80: =VLOOKUP(B80,所有人!A:Q,7,FALSE) -> 安全分析工程师 | N80: 项目实施人员 | O80: 本科 | P80: 2017/05/11 | Q80: 9 | Z80: CNITSEC2023CISE17565 | AP80: 是 | AQ80: =COUNTA(T80:AN80) -> 1
A81: 80 | B81: 黄天成 | C81: 男 | D81: AAAAAABBBBBB | E81: 139xxxxxxx | F81: =VLOOKUP(B81,所有人!A:Q,16,FALSE) -> 44092119990509451X | G81: =VLOOKUP(B81,所有人!A:Q,9,FALSE) -> 广州市 | I81: =VLOOKUP(B81,所有人!A:O,12,FALSE) -> 广东工业大学华立学院 | J81: =VLOOKUP(B81,所有人!A:O,14,FALSE) -> 计算机科学与技术 | K81: =VLOOKUP(B81,所有人!A:Q,17,FALSE) -> 2025/07/09 | L81: =DATEDIF(K81,TODAY(),"Y") -> 0 | M81: =VLOOKUP(B81,所有人!A:Q,7,FALSE) -> 大数据工程师 | N81: 项目实施人员 | O81: 本科 | P81: 2022/08/01 | Q81: 3 | AP81: 是 | AQ81: =COUNTA(T81:AN81) -> 0
A82: 81 | B82: 黄武宝 | C82: 男 | D82: AAAAAABBBBBB | E82: 139xxxxxxx | F82: =VLOOKUP(B82,所有人!A:Q,16,FALSE) -> 450821199304214930 | G82: =VLOOKUP(B82,所有人!A:Q,9,FALSE) -> 广州市 | I82: =VLOOKUP(B82,所有人!A:O,12,FALSE) -> 梧州学院 | J82: =VLOOKUP(B82,所有人!A:O,14,FALSE) -> 通信工程 | K82: =VLOOKUP(B82,所有人!A:Q,17,FALSE) -> 2023/01/03 | L82: =DATEDIF(K82,TODAY(),"Y") -> 3 | M82: =VLOOKUP(B82,所有人!A:Q,7,FALSE) -> 系统运营经理 | N82: 项目实施人员 | O82: 本科 | P82: 2019/07/01 | Q82: 6 | Z82: CNITSEC2023CISO17750 | AP82: 是 | AQ82: =COUNTA(T82:AN82) -> 1
A83: 82 | B83: 计鹏伟 | C83: 男 | D83: AAAAAABBBBBB | E83: 139xxxxxxx | F83: =VLOOKUP(B83,所有人!A:Q,16,FALSE) -> 642221198512011599 | G83: =VLOOKUP(B83,所有人!A:Q,9,FALSE) -> 银川市 | I83: =VLOOKUP(B83,所有人!A:O,12,FALSE) -> 宁夏大学 | J83: =VLOOKUP(B83,所有人!A:O,14,FALSE) -> 软件工程 | K83: =VLOOKUP(B83,所有人!A:Q,17,FALSE) -> 2021/02/22 | L83: =DATEDIF(K83,TODAY(),"Y") -> 5 | M83: =VLOOKUP(B83,所有人!A:Q,7,FALSE) -> 项目经理 | N83: 质控工程师 | O83: 本科 | P83: 2009/07/01 | Q83: 16 | AP83: 是 | AQ83: =COUNTA(T83:AN83) -> 0
A84: 83 | B84: 纪燕飞 | C84: 男 | D84: AAAAAABBBBBB | E84: 139xxxxxxx | F84: =VLOOKUP(B84,所有人!A:Q,16,FALSE) -> 62040319901108202X | G84: =VLOOKUP(B84,所有人!A:Q,9,FALSE) -> 银川市 | I84: =VLOOKUP(B84,所有人!A:O,12,FALSE) -> 天津理工大学中环信息学院 | J84: =VLOOKUP(B84,所有人!A:O,14,FALSE) -> 软件工程 | K84: =VLOOKUP(B84,所有人!A:Q,17,FALSE) -> 2016/07/14 | L84: =DATEDIF(K84,TODAY(),"Y") -> 9 | M84: =VLOOKUP(B84,所有人!A:Q,7,FALSE) -> 实施运维工程师 | N84: 项目实施人员 | O84: 本科 | P84: 2015/06/24 | Q84: 10 | AP84: 是 | AQ84: =COUNTA(T84:AN84) -> 0
A85: 84 | B85: 冀中华 | C85: 男 | D85: AAAAAABBBBBB | E85: 139xxxxxxx | F85: =VLOOKUP(B85,所有人!A:Q,16,FALSE) -> 321023199311070438 | G85: =VLOOKUP(B85,所有人!A:Q,9,FALSE) -> 南京市 | I85: =VLOOKUP(B85,所有人!A:O,12,FALSE) -> 南京邮电大学 | J85: =VLOOKUP(B85,所有人!A:O,14,FALSE) -> 控制工程 | K85: =VLOOKUP(B85,所有人!A:Q,17,FALSE) -> 2025/08/11 | L85: =DATEDIF(K85,TODAY(),"Y") -> 0 | M85: =VLOOKUP(B85,所有人!A:Q,7,FALSE) -> 解决方案经理 | N85: 项目实施人员 | O85: 硕士研究生 | P85: 2019/07/01 | Q85: 6 | AP85: 是 | AQ85: =COUNTA(T85:AN85) -> 0
A86: 85 | B86: 贾永辉 | C86: 男 | D86: AAAAAABBBBBB | E86: 139xxxxxxx | F86: =VLOOKUP(B86,所有人!A:Q,16,FALSE) -> 130130198711200316 | G86: =VLOOKUP(B86,所有人!A:Q,9,FALSE) -> 北京市 | I86: =VLOOKUP(B86,所有人!A:O,12,FALSE) -> 河北北方学院 | J86: =VLOOKUP(B86,所有人!A:O,14,FALSE) -> 通信工程 | K86: =VLOOKUP(B86,所有人!A:Q,17,FALSE) -> 2021/07/26 | L86: =DATEDIF(K86,TODAY(),"Y") -> 4 | M86: =VLOOKUP(B86,所有人!A:Q,7,FALSE) -> 资深C语言工程师 | N86: 质控工程师 | O86: 本科 | P86: 2012/07/01 | Q86: 13 | AP86: 是 | AQ86: =COUNTA(T86:AN86) -> 0
A87: 86 | B87: 姜双双 | C87: 男 | D87: AAAAAABBBBBB | E87: 139xxxxxxx | F87: =VLOOKUP(B87,所有人!A:Q,16,FALSE) -> 210213199309123942 | G87: =VLOOKUP(B87,所有人!A:Q,9,FALSE) -> 大连市 | I87: =VLOOKUP(B87,所有人!A:O,12,FALSE) -> 哈尔滨工业大学 | J87: =VLOOKUP(B87,所有人!A:O,14,FALSE) -> 电子与通信工程 | K87: =VLOOKUP(B87,所有人!A:Q,17,FALSE) -> 2021/02/24 | L87: =DATEDIF(K87,TODAY(),"Y") -> 5 | M87: =VLOOKUP(B87,所有人!A:Q,7,FALSE) -> Go语言工程师 | N87: 项目实施人员 | O87: 硕士研究生 | P87: 2018/07/23 | Q87: 7 | AP87: 是 | AQ87: =COUNTA(T87:AN87) -> 0
A88: 87 | B88: 蒋辉 | C88: 男 | D88: AAAAAABBBBBB | E88: 139xxxxxxx | F88: =VLOOKUP(B88,所有人!A:Q,16,FALSE) -> 341221199208013496 | G88: =VLOOKUP(B88,所有人!A:Q,9,FALSE) -> 广州市 | I88: =VLOOKUP(B88,所有人!A:O,12,FALSE) -> 仲恺农业工程学院 | J88: =VLOOKUP(B88,所有人!A:O,14,FALSE) -> 网络工程 | K88: =VLOOKUP(B88,所有人!A:Q,17,FALSE) -> 2015/08/03 | L88: =DATEDIF(K88,TODAY(),"Y") -> 10 | M88: =VLOOKUP(B88,所有人!A:Q,7,FALSE) -> 实施运维工程师 | N88: 项目实施人员 | O88: 本科 | P88: 2015/08/03 | Q88: 10 | AP88: 是 | AQ88: =COUNTA(T88:AN88) -> 0
A89: 88 | B89: 蒋鹏程 | C89: 男 | D89: AAAAAABBBBBB | E89: 139xxxxxxx | F89: =VLOOKUP(B89,所有人!A:Q,16,FALSE) -> 500382198409245739 | G89: =VLOOKUP(B89,所有人!A:Q,9,FALSE) -> 重庆市 | I89: =VLOOKUP(B89,所有人!A:O,12,FALSE) -> 武汉理工大学 | J89: =VLOOKUP(B89,所有人!A:O,14,FALSE) -> 通信工程 | K89: =VLOOKUP(B89,所有人!A:Q,17,FALSE) -> 2022/01/06 | L89: =DATEDIF(K89,TODAY(),"Y") -> 4 | M89: =VLOOKUP(B89,所有人!A:Q,7,FALSE) -> 实施运维工程师 | N89: 项目实施人员 | O89: 本科 | P89: 2008/03/01 | Q89: 18 | AA89: 2018CISAWRM1869 (R2) | AP89: 是 | AQ89: =COUNTA(T89:AN89) -> 1
A90: 89 | B90: 李洪兴 | C90: 男 | D90: AAAAAABBBBBB | E90: 139xxxxxxx | F90: =VLOOKUP(B90,所有人!A:Q,16,FALSE) -> 372922199410055711 | G90: =VLOOKUP(B90,所有人!A:Q,9,FALSE) -> 济南市 | I90: =VLOOKUP(B90,所有人!A:O,12,FALSE) -> 山东交通学院 | J90: =VLOOKUP(B90,所有人!A:O,14,FALSE) -> 计算机科学与技术 | K90: =VLOOKUP(B90,所有人!A:Q,17,FALSE) -> 2021/04/20 | L90: =DATEDIF(K90,TODAY(),"Y") -> 5 | M90: =VLOOKUP(B90,所有人!A:Q,7,FALSE) -> 系统运营经理 | N90: 项目实施人员 | O90: 本科 | P90: 2017/07/20 | Q90: 8 | Z90: CNITSEC2022CISE05451 | AP90: 是 | AQ90: =COUNTA(T90:AN90) -> 1
A91: 90 | B91: 李天将 | C91: 男 | D91: AAAAAABBBBBB | E91: 139xxxxxxx | F91: =VLOOKUP(B91,所有人!A:Q,16,FALSE) -> 513723199601086054 | G91: =VLOOKUP(B91,所有人!A:Q,9,FALSE) -> 长沙市 | I91: =VLOOKUP(B91,所有人!A:O,12,FALSE) -> 成都工业学院 | J91: =VLOOKUP(B91,所有人!A:O,14,FALSE) -> 通信工程 | K91: =VLOOKUP(B91,所有人!A:Q,17,FALSE) -> 2023/02/06 | L91: =DATEDIF(K91,TODAY(),"Y") -> 3 | M91: =VLOOKUP(B91,所有人!A:Q,7,FALSE) -> 解决方案经理 | N91: 测试人员 | O91: 本科 | P91: 2018/07/01 | Q91: 7 | Z91: CNITSEC2021CISE21111 | AP91: 是 | AQ91: =COUNTA(T91:AN91) -> 1
A92: 91 | B92: 李晓康 | C92: 男 | D92: AAAAAABBBBBB | E92: 139xxxxxxx | F92: =VLOOKUP(B92,所有人!A:Q,16,FALSE) -> 342601199605181036 | G92: =VLOOKUP(B92,所有人!A:Q,9,FALSE) -> 合肥市 | I92: =VLOOKUP(B92,所有人!A:O,12,FALSE) -> 安徽三联学院 | J92: =VLOOKUP(B92,所有人!A:O,14,FALSE) -> 计算机科学与技术 | K92: =VLOOKUP(B92,所有人!A:Q,17,FALSE) -> 2020/06/28 | L92: =DATEDIF(K92,TODAY(),"Y") -> 6 | M92: =VLOOKUP(B92,所有人!A:Q,7,FALSE) -> 系统可靠性监测专家 | N92: 项目实施人员 | O92: 本科 | P92: 2019/03/04 | Q92: 7 | Z92: CNITSEC2022CISO01815 | AP92: 是 | AQ92: =COUNTA(T92:AN92) -> 1
A93: 92 | B93: 梁箐洪 | C93: 男 | D93: AAAAAABBBBBB | E93: 139xxxxxxx | F93: =VLOOKUP(B93,所有人!A:Q,16,FALSE) -> 522122199606053659 | G93: =VLOOKUP(B93,所有人!A:Q,9,FALSE) -> 贵阳市 | I93: =VLOOKUP(B93,所有人!A:O,12,FALSE) -> 贵州大学 | J93: =VLOOKUP(B93,所有人!A:O,14,FALSE) -> 信息安全 | K93: =VLOOKUP(B93,所有人!A:Q,17,FALSE) -> 2022/07/01 | L93: =DATEDIF(K93,TODAY(),"Y") -> 3 | M93: =VLOOKUP(B93,所有人!A:Q,7,FALSE) -> 安全分析工程师 | N93: 项目实施人员 | O93: 本科 | P93: 2022/01/10 | Q93: 4 | AP93: 是 | AQ93: =COUNTA(T93:AN93) -> 0
A94: 93 | B94: 梁庄杰 | C94: 男 | D94: AAAAAABBBBBB | E94: 139xxxxxxx | F94: =VLOOKUP(B94,所有人!A:Q,16,FALSE) -> 431225199902231431 | G94: =VLOOKUP(B94,所有人!A:Q,9,FALSE) -> 长沙市 | I94: =VLOOKUP(B94,所有人!A:O,12,FALSE) -> 吉首大学张家界学院 | J94: =VLOOKUP(B94,所有人!A:O,14,FALSE) -> 计算机科学与技术 | K94: =VLOOKUP(B94,所有人!A:Q,17,FALSE) -> 2024/12/10 | L94: =DATEDIF(K94,TODAY(),"Y") -> 1 | M94: =VLOOKUP(B94,所有人!A:Q,7,FALSE) -> 驻场运营经理 | N94: 项目实施人员 | O94: 本科 | P94: 2021/01/08 | Q94: 5 | AP94: 是 | AQ94: =COUNTA(T94:AN94) -> 0
A95: 94 | B95: 林涛 | C95: 男 | D95: AAAAAABBBBBB | E95: 139xxxxxxx | F95: =VLOOKUP(B95,所有人!A:Q,16,FALSE) -> 51012219911118811X | G95: =VLOOKUP(B95,所有人!A:Q,9,FALSE) -> 成都市 | I95: =VLOOKUP(B95,所有人!A:O,12,FALSE) -> 电子科技大学成都学院 | J95: =VLOOKUP(B95,所有人!A:O,14,FALSE) -> 计算机科学与技术 | K95: =VLOOKUP(B95,所有人!A:Q,17,FALSE) -> 2015/05/04 | L95: =DATEDIF(K95,TODAY(),"Y") -> 11 | M95: =VLOOKUP(B95,所有人!A:Q,7,FALSE) -> 项目经理 | N95: 测试人员 | O95: 本科 | P95: 2013/08/01 | Q95: 12 | AP95: 是 | AQ95: =COUNTA(T95:AN95) -> 0
A96: 95 | B96: 林益峰1 | C96: 男 | D96: AAAAAABBBBBB | E96: 139xxxxxxx | F96: =VLOOKUP(B96,所有人!A:Q,16,FALSE) -> 350321199705100714 | G96: =VLOOKUP(B96,所有人!A:Q,9,FALSE) -> 厦门市 | I96: =VLOOKUP(B96,所有人!A:O,12,FALSE) -> 闽江学院 | J96: =VLOOKUP(B96,所有人!A:O,14,FALSE) -> 软件工程 | K96: =VLOOKUP(B96,所有人!A:Q,17,FALSE) -> 2022/07/01 | L96: =DATEDIF(K96,TODAY(),"Y") -> 3 | M96: =VLOOKUP(B96,所有人!A:Q,7,FALSE) -> 系统运营专家 | N96: 项目实施人员 | O96: 本科 | P96: 2021/01/01 | Q96: 5 | AP96: 是 | AQ96: =COUNTA(T96:AN96) -> 0
A97: 96 | B97: 林泽琛 | C97: 男 | D97: AAAAAABBBBBB | E97: 139xxxxxxx | F97: =VLOOKUP(B97,所有人!A:Q,16,FALSE) -> 440506199408030034 | G97: =VLOOKUP(B97,所有人!A:Q,9,FALSE) -> 广州市 | I97: =VLOOKUP(B97,所有人!A:O,12,FALSE) -> 惠州学院 | J97: =VLOOKUP(B97,所有人!A:O,14,FALSE) -> 网络工程 | K97: =VLOOKUP(B97,所有人!A:Q,17,FALSE) -> 2024/04/07 | L97: =DATEDIF(K97,TODAY(),"Y") -> 2 | M97: =VLOOKUP(B97,所有人!A:Q,7,FALSE) -> 跨专业支持工程师 | N97: 项目实施人员 | O97: 本科 | P97: 2017/09/01 | Q97: 8 | AP97: 是 | AQ97: =COUNTA(T97:AN97) -> 0
A98: 97 | B98: 刘超 | C98: 男 | D98: AAAAAABBBBBB | E98: 139xxxxxxx | F98: =VLOOKUP(B98,所有人!A:Q,16,FALSE) -> 412825199902031050 | G98: =VLOOKUP(B98,所有人!A:Q,9,FALSE) -> 北京市 | I98: =VLOOKUP(B98,所有人!A:O,12,FALSE) -> 郑州西亚斯学院 | J98: =VLOOKUP(B98,所有人!A:O,14,FALSE) -> 软件工程 | K98: =VLOOKUP(B98,所有人!A:Q,17,FALSE) -> 2022/11/14 | L98: =DATEDIF(K98,TODAY(),"Y") -> 3 | M98: =VLOOKUP(B98,所有人!A:Q,7,FALSE) -> 实施运维工程师 | N98: 项目实施人员 | O98: 本科 | P98: 2021/01/01 | Q98: 5 | AP98: 是 | AQ98: =COUNTA(T98:AN98) -> 0
A99: 98 | B99: 刘积磊 | C99: 男 | D99: AAAAAABBBBBB | E99: 139xxxxxxx | F99: =VLOOKUP(B99,所有人!A:Q,16,FALSE) -> 210623199204194917 | G99: =VLOOKUP(B99,所有人!A:Q,9,FALSE) -> 天津市 | I99: =VLOOKUP(B99,所有人!A:O,12,FALSE) -> 哈尔滨工程大学 | J99: =VLOOKUP(B99,所有人!A:O,14,FALSE) -> 通信工程 | K99: =VLOOKUP(B99,所有人!A:Q,17,FALSE) -> 2022/01/10 | L99: =DATEDIF(K99,TODAY(),"Y") -> 4 | M99: =VLOOKUP(B99,所有人!A:Q,7,FALSE) -> 资深C语言工程师 | N99: 测试人员 | O99: 本科 | P99: 2015/08/24 | Q99: 10 | AP99: 是 | AQ99: =COUNTA(T99:AN99) -> 0
A100: 99 | B100: 刘家楠 | C100: 男 | D100: AAAAAABBBBBB | E100: 139xxxxxxx | F100: =VLOOKUP(B100,所有人!A:Q,16,FALSE) -> 341225199605068621 | G100: =VLOOKUP(B100,所有人!A:Q,9,FALSE) -> 北京市 | I100: =VLOOKUP(B100,所有人!A:O,12,FALSE) -> 福建师范大学福清校区 | J100: =VLOOKUP(B100,所有人!A:O,14,FALSE) -> 网络工程 | K100: =VLOOKUP(B100,所有人!A:Q,17,FALSE) -> 2019/12/11 | L100: =DATEDIF(K100,TODAY(),"Y") -> 6 | M100: =VLOOKUP(B100,所有人!A:Q,7,FALSE) -> 保密专员 | N100: 项目经理 | O100: 本科 | P100: 2018/10/08 | Q100: 7 | AP100: 是 | AQ100: =COUNTA(T100:AN100) -> 0
...

Sheet 所有人
A1: 姓名 | B1: 最高学历 | C1: 出生日期 | D1: 首次参加工作时间 | E1: 一级部门名称 | F1: 二级部门名称 | G1: 岗位名称 | H1: 工作地点所在省 | I1: 工作地点所在市 | J1: 社保公积金缴纳地 | K1: 所属公司 | L1: 学校 | M1: 毕业时间 | N1: 专业 | O1: 学位 | P1: 身份证号 | Q1: 入职时间
A2: 阿曼太 | B2: 本科 | C2: 1982/11/26 | D2: 2006/09/01 | E2: 云网数据科学中心 | F2: 云网数据科学中心办公室1 | G2: 副总裁兼中心总经理 | H2: 北京市 | I2: 北京市 | J2: 北京 | K2: 北京恒安嘉新数智科技有限公司 | L2: 中央民族大学 | M2: 2006/07/01 | N2: 计算机科学与技术 | O2: 学士 | P2: 652328198211260016 | Q2: 2011/05/16
A3: 艾庆崴 | B3: 本科 | C3: 1986/08/26 | D3: 2011/02/21 | E3: 云网数据科学中心 | F3: 可信数据空间研发部 | G3: 组长 | H3: 湖北省 | I3: 武汉市 | J3: 武汉 | K3: 恒安嘉新（北京）科技股份公司 | L3: 中南财经政法大学 | M3: 2009/12/30 | N3: 金融保险 | O3: 学士 | P3: 422202198608261816 | Q3: 2021/07/01
A4: 安京玲 | B4: 本科 | C4: 1992/03/08 | D4: 2015/07/01 | E4: 证券部 | G4: 法务经理 | H4: 北京市 | I4: 北京市 | J4: 北京 | K4: 恒安嘉新（北京）科技股份公司 | L4: 河北科技师范学院 | M4: 2015/06/19 | N4: 法学 | O4: 学士 | P4: 132201199203086043 | Q4: 2017/07/26
A5: 敖仕1 | B5: 本科 | C5: 1994/04/21 | D5: 2013/10/16 | E5: 云网数据科学中心 | F5: 基础网络算力工程部 | G5: 实施运维工程师 | H5: 贵州省 | I5: 贵阳市 | J5: 北京 | K5: 恒安嘉新（北京）科技股份公司 | L5: 北京外国语大学 | M5: 2022/09/23 | N5: 信息管理与信息技术 | O5: 无 | P5: 522121199404215238 | Q5: 2025/07/07
A6: 白首骏 | B6: 本科 | C6: 1990/10/30 | D6: 2013/06/24 | E6: 云网数据科学中心 | F6: 金川-IDC/DNS智能体产品研发部 | G6: Java工程师 | H6: 北京市 | I6: 北京市 | J6: 北京 | K6: 恒安嘉新（北京）科技股份公司 | L6: 北京城市学院 | M6: 2013/06/08 | N6: 计算机科学与技术 | O6: 学士 | P6: 110101199010304031 | Q6: 2020/03/25
A7: 白喆 | B7: 本科 | C7: 1979/07/16 | D7: 2002/06/01 | E7: 市场连锁经营中心 | F7: 陕西-销售 | G7: 客户总监 | H7: 陕西省 | I7: 西安市 | J7: 西安 | K7: 恒安嘉新（北京）科技股份公司 | L7: 西安电子科技大学 | M7: 2002/06/01 | N7: 计算机应用 | O7: 学士 | P7: 612725197907163012 | Q7: 2017/02/06
A8: 班宏 | B8: 本科 | C8: 1998/10/31 | D8: 2020/08/01 | E8: 云网数据科学中心 | F8: 合成作战数据智能运营部 | G8: 系统运营经理 | H8: 广西壮族自治区 | I8: 南宁市 | J8: 南宁 | K8: 恒安嘉新（北京）科技股份公司 | L8: 广西民族师范学院 | M8: 2021/06/20 | N8: 网络工程 | O8: 学士 | P8: 452727199810310014 | Q8: 2021/05/14
A9: 鲍永昌 | B9: 本科 | C9: 1987/05/03 | D9: 2010/01/18 | E9: 云网数据科学中心 | F9: 咨询交付服务增长部 | G9: 解决方案经理 | H9: 河北省 | I9: 石家庄市 | J9: 石家庄 | K9: 恒安嘉新（北京）科技股份公司 | L9: 北京邮电大学 | M9: 2013/01/31 | N9: 通信工程 | O9: 学士 | P9: 130182198705036675 | Q9: 2018/10/08
A10: 鲍雨 | B10: 本科 | C10: 1995/08/11 | D10: 2015/06/01 | E10: 云网数据科学中心 | F10: 合成作战数据智能运营部 | G10: 系统运营专家 | H10: 江西省 | I10: 南昌市 | J10: 南昌 | K10: 恒安嘉新（北京）科技股份公司 | L10: 华南理工大学网络教育学院 | M10: 2020/01/30 | N10: 计算机科学与技术 | O10: 学士 | P10: 362201199508112831 | Q10: 2022/01/04
A11: 边桂锋 | B11: 大专及其以下 | C11: 1981/06/05 | D11: 1998/01/01 | E11: 人教行政服务中心 | F11: 行政管理部 | G11: 行政专员 | H11: 北京市 | I11: 北京市 | J11: 北京 | K11: 北京恒安嘉新数智科技有限公司 | L11: 无 | M11: 2013/01/01 | N11: 无 | O11: 无 | P11: 410781198106054154 | Q11: 2020/11/06
A12: 卜凡成1 | B12: 本科 | C12: 1994/02/01 | D12: 2016/07/01 | E12: 云网数据科学中心 | F12: 金御-工业互联网智能体产品研发部 | G12: Java工程师 | H12: 山东省 | I12: 济南市 | J12: 济南 | K12: 恒安嘉新（北京）科技股份公司 | L12: 山东理工大学 | M12: 2016/07/01 | N12: 电子信息科学与技术 | O12: 学士 | P12: 371102199402017512 | Q12: 2021/06/01
A13: 步学剑 | B13: 本科 | C13: 1992/08/24 | D13: 2015/10/10 | E13: 云网数据科学中心 | F13: 金御-网综智能体产品研发部 | G13: Java工程师 | H13: 天津市 | I13: 天津市 | J13: 天津 | K13: 恒安嘉新（北京）科技股份公司 | L13: 湖南农业大学 | M13: 2015/06/30 | N13: 食品科学与工程 | O13: 学士 | P13: 120222199208243616 | Q13: 2023/04/12
A14: 蔡骏潇 | B14: 本科 | C14: 1990/08/05 | D14: 2013/08/08 | E14: 云网数据科学中心 | F14: 咨询交付服务增长部 | G14: 解决方案经理 | H14: 宁夏回族自治区 | I14: 银川市 | J14: 银川 | K14: 恒安嘉新（北京）科技股份公司 | L14: 西安邮电大学 | M14: 2017/12/22 | N14: 电子与通信工程 | O14: 硕士 | P14: 640102199008051514 | Q14: 2021/06/16
A15: 蔡小龙 | B15: 本科 | C15: 1989/08/30 | D15: 2011/07/12 | E15: 云网数据科学中心 | F15: 合成作战数据智能运营部 | G15: 跨专业支持工程师 | H15: 宁夏回族自治区 | I15: 银川市 | J15: 银川 | K15: 恒安嘉新（北京）科技股份公司 | L15: 北京邮电大学 | M15: 2011/06/23 | N15: 电子信息工程 | O15: 学士 | P15: 640302198908300711 | Q15: 2023/02/06
A16: 蔡晓勇 | B16: 本科 | C16: 1991/06/11 | D16: 2014/08/01 | E16: 云网数据科学中心 | F16: 合成作战数据智能运营部 | G16: 系统运营经理 | H16: 福建省 | I16: 福州市 | J16: 福州 | K16: 恒安嘉新（北京）科技股份公司 | L16: 福建工程学院 | M16: 2014/06/20 | N16: 电子信息工程 | O16: 学士 | P16: 350302199106113119 | Q16: 2026/04/01
... A54: 陈炜 | B54: 大专及其以下 | C54: 1978/05/18 | D54: 1996/09/16 | E54: 市场连锁经营中心 | F54: 福建-销售 | G54: 客户总监 | H54: 福建省 | I54: 福州市 | J54: 福州 | K54: 恒安嘉新（北京）科技股份公司 | L54: 湖南大学 | M54: 2003/12/01 | N54: 法学 | O54: 无 | P54: 352201197805180039 | Q54: 2020/12/04
A55: 陈晓光 | B55: 硕士研究生 | C55: 1982/10/24 | D55: 2008/07/01 | E55: CEO办 | G55: CEO | H55: 北京市 | I55: 北京市 | J55: 北京 | K55: 北京恒安嘉新数智科技有限公司 | L55: 北京邮电大学 | M55: 2008/04/20 | N55: 信息安全 | O55: 硕士 | P55: 130103198210241276 | Q55: 2010/10/01
A56: 陈晓鹏 | B56: 本科 | C56: 1973/07/13 | D56: 1997/09/01 | E56: 云网数据科学中心 | F56: Dev&LLMOps研发 | G56: Go语言工程师 | H56: 北京市 | I56: 北京市 | J56: 北京 | K56: 恒安嘉新（北京）科技股份公司 | L56: 清华大学 | M56: 1997/07/01 | N56: 电子工程 | O56: 学士 | P56: 110105197307130817 | Q56: 2021/06/02
A57: 陈雅琴 | B57: 硕士研究生 | C57: 1977/10/17 | D57: 2000/07/01 | E57: 保密管理办公室 | G57: 保密总监 | H57: 北京市 | I57: 北京市 | J57: 北京 | K57: 恒安嘉新（北京）科技股份公司 | L57: 北京师范大学 | M57: 2024/06/30 | N57: 工商管理 | O57: 硕士 | P57: 421002197710170025 | Q57: 2020/07/09
A58: 陈扬 | B58: 本科 | C58: 1991/01/30 | D58: 2012/08/15 | E58: 云网数据科学中心 | F58: 咨询交付专家部 | G58: 解决方案专家 | H58: 陕西省 | I58: 西安市 | J58: 西安 | K58: 恒安嘉新（北京）科技股份公司 | L58: 西安邮电大学 | M58: 2012/07/05 | N58: 光电信息工程 | O58: 学士 | P58: 610528199101300036 | Q58: 2019/05/27
A59: 陈杨1 | B59: 本科 | C59: 1993/08/08 | D59: 2016/06/01 | E59: 云网数据科学中心 | F59: 数智产品架构部 | G59: 产品设计专家 | H59: 湖北省 | I59: 武汉市 | J59: 武汉 | K59: 恒安嘉新（北京）科技股份公司 | L59: 湖北汽车工业学院 | M59: 2016/06/01 | N59: 工业设计 | O59: 学士 | P59: 421121199308082020 | Q59: 2021/06/01
A60: 陈永坤 | B60: 本科 | C60: 1996/11/13 | D60: 2018/07/01 | E60: 云网数据科学中心 | F60: 网络安全模型研发部 | G60: 安全分析工程师 | H60: 山东省 | I60: 济南市 | J60: 济南 | K60: 恒安嘉新（北京）科技股份公司 | L60: 江西理工大学 | M60: 2019/06/01 | N60: 信息安全 | O60: 学士 | P60: 412727199611134030 | Q60: 2020/12/14
A61: 陈宇 | B61: 硕士研究生 | C61: 1975/05/05 | D61: 1998/09/01 | E61: 云网数据科学中心 | F61: 咨询交付服务增长部 | G61: 解决方案经理 | H61: 内蒙古自治区 | I61: 呼和浩特市 | J61: 北京 | K61: 恒安嘉新（北京）科技股份公司 | L61: 内蒙古大学 | M61: 2009/04/01 | N61: 工商管理 | O61: 硕士 | P61: 150103197505051030 | Q61: 2020/09/14
A62: 陈宇鹏1 | B62: 本科 | C62: 1999/11/05 | D62: 2021/12/01 | E62: 云网数据科学中心 | F62: 基础网络算力工程部 | G62: 实施运维工程师 | H62: 福建省 | I62: 厦门市 | J62: 福州 | K62: 恒安嘉新（北京）科技股份公司 | L62: 西安电子科技大学 | M62: 2021/06/23 | N62: 信息安全 | O62: 学士 | P62: 35058319991105603X | Q62: 2022/08/01
A63: 陈曾 | B63: 大专及其以下 | C63: 1997/01/18 | D63: 2016/07/14 | E63: 云网数据科学中心 | F63: 合成作战数据智能运营部 | G63: 系统运营经理 | H63: 上海市 | I63: 上海市 | J63: 上海 | K63: 恒安嘉新（上海）科技有限公司 | L63: 武汉警官职业学院 | M63: 2017/06/15 | N63: 计算机网络技术 | O63: 无 | P63: 420117199701180019 | Q63: 2022/03/22
A64: 陈钊2 | B64: 本科 | C64: 1993/06/03 | D64: 2017/03/20 | E64: 云网数据科学中心 | F64: 金御-工业互联网智能体产品研发部 | G64: Java工程师 | H64: 山东省 | I64: 济南市 | J64: 济南 | K64: 恒安嘉新（北京）科技股份公司 | L64: 山东工商学院 | M64: 2017/06/01 | N64: 计算机科学与技术 | O64: 学士 | P64: 372328199306030333 | Q64: 2021/07/05
A65: 陈振 | B65: 本科 | C65: 1985/07/19 | D65: 2009/09/21 | E65: 云网数据科学中心 | F65: 通信网安全模型研发部 | G65: 大数据工程师 | H65: 广东省 | I65: 广州市 | J65: 广州 | K65: 恒安嘉新（北京）科技股份公司 | L65: 河南理工大学 | M65: 2009/07/03 | N65: 计算机科学与技术 | O65: 学士 | P65: 411481198507199017 | Q65: 2018/07/24
A66: 成春鸽 | B66: 本科 | C66: 1981/03/18 | D66: 2003/03/24 | E66: 云网数据科学中心 | F66: 基础网络算力工程部 | G66: 实施运维工程师 | H66: 上海市 | I66: 上海市 | J66: 上海 | K66: 恒安嘉新（上海）科技有限公司 | L66: 复旦大学 | M66: 2011/06/30 | N66: 计算机网络 | O66: 无 | P66: 430422198103181219 | Q66: 2023/02/27
A67: 程利明 | B67: 大专及其以下 | C67: 1984/10/22 | D67: 2008/05/01 | E67: 云网数据科学中心 | F67: 合成作战数据智能运营部 | G67: 系统运营经理 | H67: 湖北省 | I67: 武汉市 | J67: 北京 | K67: 恒安嘉新（北京）科技股份公司 | L67: 河北金融学院 | M67: 2008/05/01 | N67: 计算机 | O67: 无 | P67: 422326198410225517 | Q67: 2012/07/02
A68: 仇红建1 | B68: 本科 | C68: 1988/01/05 | D68: 2010/06/23 | E68: 云网数据科学中心 | F68: 合成作战数据智能运营部 | G68: 跨专业支持工程师 | H68: 天津市 | I68: 天津市 | J68: 天津 | K68: 恒安嘉新（北京）科技股份公司 | L68: 天津理工大学 | M68: 2010/06/21 | N68: 光信息科学与技术 | O68: 学士 | P68: 120225198801053316 | Q68: 2022/07/28
A69: 从继通 | B69: 本科 | C69: 1985/10/15 | D69: 2008/07/07 | E69: 云网数据科学中心 | F69: 金御-网综智能体产品研发部 | G69: Java工程师 | H69: 天津市 | I69: 天津市 | J69: 天津 | K69: 恒安嘉新（北京）科技股份公司 | L69: 大连民族学院 | M69: 2008/06/30 | N69: 软件工程 | O69: 学士 | P69: 12010119851015353X | Q69: 2019/05/08
... A106: 范晓波 | B106: 本科 | C106: 1992/03/04 | D106: 2016/02/14 | E106: 云网数据科学中心 | F106: 云河-零信任企业安全产品研发部 | G106: Go语言工程师 | H106: 北京市 | I106: 北京市 | J106: 北京 | K106: 恒安嘉新（北京）科技股份公司 | L106: 太原工业学院 | M106: 2016/07/01 | N106: 自动化 | O106: 学士 | P106: 142325199203045514 | Q106: 2020/11/09
A107: 范旭 | B107: 大专及其以下 | C107: 1987/09/23 | D107: 2010/10/08 | E107: 用户体验研发中心 | G107: UI设计师 | H107: 河北省 | I107: 雄安 | J107: 雄安 | K107: 恒安嘉新（雄安）数智科技有限公司 | L107: 秦皇岛职业技术学院 | M107: 2010/01/01 | N107: 视觉传达 | O107: 无 | P107: 130181198709237929 | Q107: 2015/09/23
A108: 范志华 | B108: 大专及其以下 | C108: 1981/09/04 | D108: 2003/12/01 | E108: 云网数据科学中心 | F108: 合成作战数据智能运营部 | G108: 系统运营经理 | H108: 山东省 | I108: 济南市 | J108: 济南 | K108: 恒安嘉新（北京）科技股份公司 | L108: 江西财经理工学院 | M108: 2003/07/01 | N108: 计算机 | O108: 无 | P108: 412721198109041434 | Q108: 2015/12/28
A109: 方心蕊 | B109: 本科 | C109: 1994/06/03 | D109: 2015/05/01 | E109: 市场连锁经营中心 | F109: 增值连锁经营管理部 | G109: 市场副总监 | H109: 北京市 | I109: 北京市 | J109: 北京 | K109: 北京恒安嘉新数智科技有限公司 | L109: 华北科技学院 | M109: 2015/07/01 | N109: 新闻学 | O109: 学士 | P109: 15210419940603032X | Q109: 2019/04/04
A110: 方渝鑫 | B110: 本科 | C110: 1994/05/08 | D110: 2017/04/01 | E110: 云网数据科学中心 | F110: 合成作战数据智能运营部 | G110: 系统运营经理 | H110: 西藏自治区 | I110: 拉萨市 | J110: 拉萨 | K110: 恒安嘉新（北京）科技股份公司 | L110: 重庆大学 | M110: 2024/07/01 | N110: 计算机科学与技术 | O110: 学士 | P110: 500102199405088459 | Q110: 2025/04/08
A111: 方宇 | B111: 硕士研究生 | C111: 1987/05/21 | D111: 2013/08/01 | E111: 财经管理服务中心 | F111: 财经管理服务中心办公室 | G111: 财务副总监 | H111: 北京市 | I111: 北京市 | J111: 北京 | K111: 恒安嘉新（北京）科技股份公司 | L111: 北京工商大学 | M111: 2013/06/30 | N111: 财务管理 | O111: 硕士 | P111: 152102198705212716 | Q111: 2026/04/01
A112: 方子玉 | B112: 硕士研究生 | C112: 1997/04/23 | D112: 2025/06/15 | E112: 云网数据科学中心 | F112: 金川-IDC/DNS智能体产品研发部 | G112: AI算法工程师 | H112: 湖北省 | I112: 武汉市 | J112: 武汉 | K112: 国嘉网信（武汉）安全技术有限公司 | L112: 华南师范大学 | M112: 2025/06/01 | N112: 计算机科学与技术 | O112: 硕士 | P112: 420104199704231617 | Q112: 2026/03/24
A113: 冯杰 | B113: 本科 | C113: 1989/05/15 | D113: 2014/06/10 | E113: 云网数据科学中心 | F113: 合成作战数据智能运营部 | G113: 系统运营经理 | H113: 河南省 | I113: 郑州市 | J113: 郑州 | K113: 恒安嘉新（北京）科技股份公司 | L113: 河南工业大学 | M113: 2014/12/30 | N113: 模具设计与制造 | O113: 学士 | P113: 41272619890515639X | Q113: 2022/10/17
A114: 冯亚南 | B114: 本科 | C114: 1989/06/06 | D114: 2010/10/14 | E114: 云网数据科学中心 | F114: 产品全连接全生命周期研用部 | G114: 项目经理 | H114: 河南省 | I114: 郑州市 | J114: 北京 | K114: 恒安嘉新（北京）科技股份公司 | L114: 中国管理软件学院 | M114: 2010/07/31 | N114: 计算机控制及应用 | O114: 无 | P114: 37292219890606609X | Q114: 2012/01/05
A115: 冯振雄 | B115: 本科 | C115: 1990/10/24 | D115: 2016/04/01 | E115: 云网数据科学中心 | F115: 金御-融合反诈智能体产品研发部 | G115: 前端工程师 | H115: 广东省 | I115: 广州市 | J115: 广州 | K115: 恒安嘉新（北京）科技股份公司 | L115: 北京师范大学珠海分校 | M115: 2016/07/01 | N115: 软件工程 | O115: 学士 | P115: 440882199010240632 | Q115: 2021/05/10
A116: 冯志超 | B116: 本科 | C116: 1986/08/14 | D116: 2008/09/01 | E116: 云网数据科学中心 | F116: 云河-零信任企业安全产品研发部 | G116: Go语言工程师 | H116: 辽宁省 | I116: 大连市 | J116: 大连 | K116: 恒安嘉新（北京）科技股份公司 | L116: 辽宁大学 | M116: 2008/07/01 | N116: 电子信息科学与技术 | O116: 学士 | P116: 210882198608140671 | Q116: 2026/01/15
A117: 符式轩 | B117: 本科 | C117: 1989/03/03 | D117: 2012/07/30 | E117: 市场连锁经营中心 | F117: 海南-销售 | G117: 区域首席客户经理 | H117: 海南省 | I117: 海口市 | J117: 海口 | K117: 恒安嘉新（北京）科技股份公司 | L117: 中国矿业大学 | M117: 2012/06/29 | N117: 计算机科学与技术 | O117: 学士 | P117: 460022198903032717 | Q117: 2026/02/02
A118: 付浩然 | B118: 本科 | C118: 1998/11/04 | D118: 2022/01/05 | E118: 云网数据科学中心 | F118: 反网络诈骗模型研发部 | G118: 安全分析工程师 | H118: 贵州省 | I118: 贵阳市 | J118: 贵阳 | K118: 恒安嘉新（北京）科技股份公司 | L118: 贵州师范大学 | M118: 2022/06/06 | N118: 电子信息工程 | O118: 学士 | P118: 520102199811043815 | Q118: 2022/07/01
A119: 付金星 | B119: 本科 | C119: 1990/11/16 | D119: 2014/07/10 | E119: 云网数据科学中心 | F119: 咨询交付服务增长部 | G119: 解决方案经理 | H119: 江苏省 | I119: 南京市 | J119: 南京 | K119: 恒安嘉新（北京）科技股份公司 | L119: 重庆邮电大学 | M119: 2014/06/20 | N119: 电子信息工程 | O119: 学士 | P119: 342221199011166537 | Q119: 2020/12/01
... A203: 焦辉远 | B203: 本科 | C203: 1997/08/18 | D203: 2021/01/18 | E203: 云网数据科学中心 | F203: 合成作战数据智能运营部 | G203: 系统运营经理 | H203: 山东省 | I203: 济南市 | J203: 济南 | K203: 恒安嘉新（北京）科技股份公司 | L203: 山东青年政治学院 | M203: 2020/06/30 | N203: 计算机科学与技术 | O203: 学士 | P203: 370982199708184975 | Q203: 2023/03/20
A204: 金红 | B204: 本科 | C204: 1966/01/01 | D204: 1984/01/01 | E204: CEO办 | G204: 董事长 | H204: 北京市 | I204: 北京市 | J204: 不缴纳 | K204: 恒安嘉新（北京）科技股份公司 | L204: 北京联合大学 | M204: 1987/07/01 | N204: 交通信号与控制 | O204: 学士 | P204: 110108196601013720 | Q204: 2010/04/01
A205: 金焕希1 | B205: 硕士研究生 | C205: 1986/08/15 | D205: 2009/07/01 | E205: 质量管理部 | G205: 质量管理经理 | H205: 北京市 | I205: 北京市 | J205: 北京 | K205: 北京恒安嘉新数智科技有限公司 | L205: Stevens Institute of Technology | M205: 2021/05/26 | N205: 企业项目管理 | O205: 硕士 | P205: 452230198608150025 | Q205: 2023/04/10
A206: 金建龙 | B206: 本科 | C206: 1989/03/22 | D206: 2013/11/10 | E206: 数据智能采集与标注研发中心 | F206: 数据智能基础采集研发部 | G206: C语言工程师 | H206: 北京市 | I206: 北京市 | J206: 北京 | K206: 恒安嘉新（北京）科技股份公司 | L206: 大连市交通大学 | M206: 2013/06/30 | N206: 信息管理与信息系统+软件工程 | O206: 学士 | P206: 21021119890322401X | Q206: 2017/07/05
A207: 金千俊 | B207: 大专及其以下 | C207: 1983/08/11 | D207: 2005/07/01 | E207: 云网数据科学中心 | F207: 产品全连接全生命周期研用部 | G207: 项目经理 | H207: 浙江省 | I207: 杭州市 | J207: 杭州 | K207: 恒安嘉新（北京）科技股份公司 | L207: 丽水学院 | M207: 2005/07/01 | N207: 计算机信息管理 | O207: 无 | P207: 330719198308115578 | Q207: 2021/04/06
A208: 金扬 | B208: 硕士研究生 | C208: 1972/11/08 | D208: 1996/07/01 | E208: 市场连锁经营中心 | F208: 增值连锁经营管理部 | G208: 事业部副总经理 | H208: 北京市 | I208: 北京市 | J208: 北京 | K208: 恒安嘉新（北京）科技股份公司 | L208: 格拉斯哥卡利多尼安大学 | M208: 2001/07/02 | N208: 信息管理 | O208: 硕士 | P208: 110108197211083779 | Q208: 2017/10/09
A209: 金钊 | C209: 1986/07/10 | D209: 2008/09/01 | E209: 市场连锁经营中心 | F209: 央企铁塔能源事业部（国际业务部） | G209: 客户经理 | H209: 河北省 | I209: 雄安 | J209: 雄安 | K209: 恒安嘉新（雄安）数智科技有限公司 | P209: 650102198607106019 | Q209: 2026/01/04
A210: 晋林涛 | B210: 本科 | C210: 1998/02/28 | D210: 2019/10/15 | E210: 云网数据科学中心 | F210: 合成作战数据智能运营部 | G210: 系统运营经理 | H210: 北京市 | I210: 北京市 | J210: 北京 | K210: 恒安嘉新（北京）科技股份公司 | L210: 山西应用科技学院 | M210: 2019/06/01 | N210: 计算机科学与技术 | O210: 学士 | P210: 14273019980228101X | Q210: 2022/01/04
A211: 康丽 | B211: 本科 | C211: 1990/02/09 | D211: 2012/10/20 | E211: 云网数据科学中心 | F211: 合成作战数据智能运营部 | G211: 系统运营专家 | H211: 辽宁省 | I211: 沈阳市 | J211: 沈阳 | K211: 恒安嘉新（北京）科技股份公司 | L211: 辽宁科技大学 | M211: 2012/07/01 | N211: 通信工程 | O211: 学士 | P211: 210682199002094766 | Q211: 2017/12/11
A212: 孔滨 | B212: 本科 | C212: 1999/04/27 | D212: 2021/06/09 | E212: 战略发展和合作生态中心 | F212: 供应链发展和合作生态部 | G212: 采购专员 | H212: 湖北省 | I212: 武汉市 | J212: 北京 | K212: 恒安嘉新（北京）科技股份公司 | L212: 河北科技大学理工学院 | M212: 2021/06/16 | N212: 电子信息工程 | O212: 学士 | P212: 130581199904271424 | Q212: 2022/01/12
A213: 孔繁桢 | B213: 本科 | C213: 1999/04/25 | D213: 2021/08/20 | E213: 云网数据科学中心 | F213: 反网络诈骗模型研发部 | G213: 安全分析工程师 | H213: 贵州省 | I213: 贵阳市 | J213: 贵阳 | K213: 恒安嘉新（北京）科技股份公司 | L213: 哈尔滨信息工程学院 | M213: 2022/02/06 | N213: 软件工程 | O213: 学士 | P213: 230422199904250015 | Q213: 2022/07/01
A214: 孔利卫 | B214: 本科 | C214: 1985/03/07 | D214: 2007/02/05 | E214: 云网数据科学中心 | F214: 合成作战数据智能运营部 | G214: 系统运营经理 | H214: 河北省 | I214: 石家庄市 | J214: 北京 | K214: 恒安嘉新（北京）科技股份公司 | L214: 北京大学 | M214: 2015/07/10 | N214: 信息管理与信息系统 | O214: 无 | P214: 130434198503076535 | Q214: 2022/07/25
A215: 孔觅 | B215: 本科 | C215: 1983/03/06 | D215: 2004/06/18 | E215: 人教行政服务中心 | F215: 行政管理部 | G215: 行政经理 | H215: 北京市 | I215: 北京市 | J215: 北京 | K215: 恒安嘉新（北京）科技股份公司 | L215: 北京印刷学院 | M215: 2011/06/30 | N215: 编辑出版学 | O215: 无 | P215: 310110198303060623 | Q215: 2019/10/08
A216: 孔庆帅 | B216: 本科 | C216: 1988/11/12 | D216: 2012/12/18 | E216: 云网数据科学中心 | F216: 金川-恶意/僵木蠕智能体产品研发部 | G216: Java工程师 | H216: 北京市 | I216: 北京市 | J216: 北京 | K216: 北京恒安嘉新数智科技有限公司 | L216: 山西省运城学院 | M216: 2012/07/14 | N216: 计算机科学与技术 | O216: 学士 | P216: 142431198811125110 | Q216: 2018/05/14
A217: 孔哲 | B217: 本科 | C217: 1989/06/21 | D217: 2012/07/01 | E217: 市场连锁经营中心 | F217: 政府监管事业部 | G217: 客户经理 | H217: 北京市 | I217: 北京市 | J217: 北京 | K217: 北京恒安嘉新数智科技有限公司 | L217: 黑龙江工程学院 | M217: 2012/09/01 | N217: 测绘工程 | O217: 学士 | P217: 230102198906211910 | Q217: 2013/08/26
A218: 况文豪1 | B218: 本科 | C218: 1991/03/14 | D218: 2014/08/04 | E218: 云网数据科学中心 | F218: 通信网安全模型研发部 | G218: 大数据工程师 | H218: 新疆维吾尔自治区 | I218: 乌鲁木齐市 | J218: 乌鲁木齐 | K218: 恒安嘉新（北京）科技股份公司 | L218: 新疆大学 | M218: 2016/07/07 | N218: 软件工程 | O218: 无 | P218: 654101199103141170 | Q218: 2026/01/04
A219: 来瑶瑶 | B219: 本科 | C219: 1993/03/15 | D219: 2014/07/02 | E219: 云网数据科学中心 | F219: 合成作战数据智能运营部 | G219: 系统运营专家 | H219: 湖北省 | I219: 武汉市 | J219: 武汉 | K219: 恒安嘉新（北京）科技股份公司 | L219: 北京大学 | M219: 2021/06/30 | N219: 计算机技术与应用 | O219: 学士 | P219: 420821199303154053 | Q219: 2022/03/07
A220: 赖家豪 | B220: 本科 | C220: 1985/02/28 | D220: 2004/07/19 | E220: 云网数据科学中心 | F220: 合成作战数据智能运营部 | G220: 系统运营经理 | H220: 广东省 | I220: 广州市 | J220: 广州 | K220: 恒安嘉新（北京）科技股份公司 | L220: 中山大学 | M220: 2018/01/10 | N220: 通信工程 | O220: 无 | P220: 440103198502283411 | Q220: 2015/11/09
A221: 雷霆 | B221: 本科 | C221: 1983/08/21 | D221: 2008/07/01 | E221: 数据智能采集与标注研发中心 | F221: 数据智能基础采集优化部 | G221: 研发总监兼高级架构师 | H221: 贵州省 | I221: 贵阳市 | J221: 北京 | K221: 北京恒安嘉新数智科技有限公司 | L221: 吉林大学 | M221: 2008/07/01 | N221: 计算机科学与技术 | O221: 无 | P221: 522625198308210056 | Q221: 2011/07/11
... A225: 李彬 | B225: 本科 | C225: 1981/03/29 | D225: 2005/11/01 | E225: 云网数据科学中心 | F225: 数智产品架构部 | G225: 产品经理 | H225: 贵州省 | I225: 贵阳市 | J225: 贵阳 | K225: 恒安嘉新（北京）科技股份公司 | L225: 四川农业大学 | M225: 2005/06/25 | N225: 经济学 | O225: 学士 | P225: 412701198103291533 | Q225: 2026/05/18
A226: 李博 | B226: 本科 | C226: 1987/03/02 | D226: 2012/03/15 | E226: 用户体验研发中心 | G226: 平面设计师 | H226: 北京市 | I226: 北京市 | J226: 北京 | K226: 北京恒安嘉新数智科技有限公司 | L226: 太原理工大学 | M226: 2011/07/10 | N226: 动画 | O226: 学士 | P226: 140108198703024230 | Q226: 2017/05/15
A227: 李博2 | B227: 大专及其以下 | C227: 1990/12/02 | D227: 2015/03/01 | E227: 云网数据科学中心 | F227: 金御-融合反诈智能体产品研发部 | G227: 前端工程师 | H227: 湖北省 | I227: 武汉市 | J227: 武汉 | K227: 国嘉网信（武汉）安全技术有限公司 | L227: 湖南文理学院 | M227: 2021/07/01 | N227: 物联网应用技术 | O227: 无 | P227: 420821199012024013 | Q227: 2021/10/08
A228: 李博文 | B228: 硕士研究生 | C228: 1993/06/01 | D228: 2020/04/12 | E228: 市场连锁经营中心 | F228: 广东-销售 | G228: 客户经理 | H228: 广东省 | I228: 广州市 | J228: 广州 | K228: 恒安嘉新（北京）科技股份公司 | L228: 昆士兰大学 | M228: 2018/12/28 | N228: 信息工程 | O228: 硕士 | P228: 220203199306012728 | Q228: 2021/09/13
A229: 李超群 | B229: 硕士研究生 | C229: 1997/05/20 | D229: 2023/06/26 | E229: 数据智能采集与标注研发中心 | F229: 数据智能基础采集研发部 | G229: C语言工程师 | H229: 北京市 | I229: 北京市 | J229: 北京 | K229: 恒安嘉新（北京）科技股份公司 | L229: 西南科技大学 | M229: 2023/12/01 | N229: 计算机科学与技术 | O229: 硕士 | P229: 140211199705201315 | Q229: 2024/01/15
A230: 李闯 | B230: 本科 | C230: 1994/10/26 | D230: 2016/03/24 | E230: 云网数据科学中心 | F230: 金御-工业互联网智能体产品研发部 | G230: Java工程师 | H230: 北京市 | I230: 北京市 | J230: 北京 | K230: 恒安嘉新（北京）科技股份公司 | L230: 西安培华学院 | M230: 2016/07/01 | N230: 计算机科学与技术 | O230: 学士 | P230: 142729199410264215 | Q230: 2021/08/02
A231: 李成圆 | B231: 本科 | C231: 1979/11/01 | D231: 2003/07/16 | E231: 市场连锁经营中心 | F231: 宁夏-销售 | G231: 客户副总监 | H231: 宁夏回族自治区 | I231: 银川市 | J231: 北京 | K231: 恒安嘉新（北京）科技股份公司 | L231: 北京邮电大学 | M231: 2003/09/11 | N231: 通信工程 | O231: 学士 | P231: 642124197911013718 | Q231: 2009/12/01
A232: 李大健 | B232: 本科 | C232: 1986/06/19 | D232: 2011/01/01 | E232: 云网数据科学中心 | F232: 合成作战数据智能运营部 | G232: 系统运营经理 | H232: 浙江省 | I232: 杭州市 | J232: 杭州 | K232: 恒安嘉新（北京）科技股份公司 | L232: 郑州轻工业学院 | M232: 2010/07/01 | N232: 自动化 | O232: 学士 | P232: 22038119860619181X | Q232: 2019/09/02
A233: 李锋 | B233: 本科 | C233: 1995/02/05 | D233: 2018/08/08 | E233: 云网数据科学中心 | F233: 网络安全模型研发部 | G233: 安全分析工程师 | H233: 山东省 | I233: 济南市 | J233: 济南 | K233: 恒安嘉新（北京）科技股份公司 | L233: 山东科技大学 | M233: 2019/06/22 | N233: 网络工程 | O233: 学士 | P233: 370481199502057010 | Q233: 2021/12/09
A234: 李光耀 | B234: 本科 | C234: 2003/02/17 | D234: 2025/03/10 | E234: 云网数据科学中心 | F234: 基础网络算力工程部 | G234: 实施运维工程师 | H234: 山东省 | I234: 济南市 | J234: 济南 | K234: 恒安嘉新（北京）科技股份公司 | L234: 山东交通学院 | M234: 2025/07/01 | N234: 信息与计算科学 | O234: 学士 | P234: 371702200302171019 | Q234: 2025/12/01
A235: 李国佳 | B235: 大专及其以下 | C235: 2001/09/23 | D235: 2022/02/24 | E235: 云网数据科学中心 | F235: 合成作战数据智能运营部 | G235: 系统运营经理 | H235: 北京市 | I235: 北京市 | J235: 北京 | K235: 北京恒安嘉新数智科技有限公司 | L235: 中国石油大学（北京） | M235: 2020/07/01 | N235: 计算机科学与技术 | O235: 无 | P235: 132623200109231027 | Q235: 2022/02/24
A236: 李国健 | B236: 本科 | C236: 1987/07/19 | D236: 2011/06/01 | E236: 云网数据科学中心 | F236: 合成作战数据智能运营部 | G236: 系统运营经理 | H236: 北京市 | I236: 北京市 | J236: 北京 | K236: 北京恒安嘉新数智科技有限公司 | L236: 郑州大学 | M236: 2011/06/01 | N236: 计算机科学与技术 | O236: 学士 | P236: 410883198707192518 | Q236: 2019/01/02
A237: 李洪兴 | B237: 本科 | C237: 1994/10/05 | D237: 2017/07/20 | E237: 云网数据科学中心 | F237: 合成作战数据智能运营部 | G237: 系统运营经理 | H237: 山东省 | I237: 济南市 | J237: 济南 | K237: 恒安嘉新（北京）科技股份公司 | L237: 山东交通学院 | M237: 2018/07/01 | N237: 计算机科学与技术 | O237: 学士 | P237: 372922199410055711 | Q237: 2021/04/20
A238: 李虎 | B238: 本科 | C238: 1990/06/02 | D238: 2013/09/10 | E238: 云网数据科学中心 | F238: 云河-数智平台赋能云研运部 | G238: Java工程师 | H238: 北京市 | I238: 北京市 | J238: 北京 | K238: 恒安嘉新（北京）科技股份公司 | L238: 北京航空航天大学 | M238: 2018/01/01 | N238: 计算机科学与技术 | O238: 无 | P238: 320325199006027853 | Q238: 2017/03/20
... A274: 李亚南2 | B274: 本科 | C274: 1994/10/16 | D274: 2017/03/01 | E274: 云网数据科学中心 | F274: 金川-IDC/DNS智能体产品研发部 | G274: Java工程师 | H274: 北京市 | I274: 北京市 | J274: 北京 | K274: 恒安嘉新（北京）科技股份公司 | L274: 长春师范大学 | M274: 2017/06/01 | N274: 软件工程 | O274: 学士 | P274: 140212199410161025 | Q274: 2022/02/22
A275: 李彦龙 | B275: 本科 | C275: 1983/09/20 | D275: 2007/07/01 | E275: 质量管理部 | G275: 资质经理 | H275: 北京市 | I275: 北京市 | J275: 北京 | K275: 恒安嘉新（北京）科技股份公司 | L275: 黑龙江大学 | M275: 2007/07/01 | N275: 统计学 | O275: 学士 | P275: 230125198309203554 | Q275: 2020/12/07
A276: 李阳阳 | B276: 本科 | C276: 1992/11/25 | D276: 2014/08/01 | E276: 云网数据科学中心 | F276: 合成作战数据智能运营部 | G276: 系统运营经理 | H276: 湖南省 | I276: 长沙市 | J276: 长沙 | K276: 恒安嘉新（北京）科技股份公司 | L276: 湖南理工学院 | M276: 2014/06/30 | N276: 计算机科学与技术 | O276: 学士 | P276: 430726199211250046 | Q276: 2026/02/02
A277: 李永生 | B277: 大专及其以下 | C277: 1984/08/31 | D277: 2007/05/15 | E277: 云网数据科学中心 | F277: 合成作战数据智能运营部 | G277: 系统运营专家 | H277: 四川省 | I277: 成都市 | J277: 北京 | K277: 恒安嘉新（北京）科技股份公司 | L277: 电子科技大学 | M277: 2007/07/05 | N277: 计算机及应用 | O277: 无 | P277: 511011198408313198 | Q277: 2017/02/22
A278: 李勇 | B278: 本科 | C278: 1991/02/21 | D278: 2015/07/10 | E278: 云网数据科学中心 | F278: 咨询交付专家部 | G278: 解决方案专家 | H278: 北京市 | I278: 北京市 | J278: 北京 | K278: 恒安嘉新（北京）科技股份公司 | L278: 河南工业大学 | M278: 2016/06/10 | N278: 工程管理 | O278: 学士 | P278: 411425199102216919 | Q278: 2020/12/28
A279: 李浴贵 | B279: 本科 | C279: 1980/04/22 | D279: 2005/07/28 | E279: 数据智能采集与标注研发中心 | F279: 数据智能基础采集研发部 | G279: 资深硬件工程师 | H279: 北京市 | I279: 北京市 | J279: 北京 | K279: 恒安嘉新（北京）科技股份公司 | L279: 山西师范大学 | M279: 2005/07/06 | N279: 计算机科学与技术 | O279: 学士 | P279: 142424198004223810 | Q279: 2021/05/10
A280: 李远洋 | B280: 本科 | C280: 1983/11/29 | D280: 2007/03/01 | E280: 云网数据科学中心 | F280: 数智产品架构部 | G280: 产品设计专家 | H280: 河南省 | I280: 郑州市 | J280: 郑州 | K280: 恒安嘉新（北京）科技股份公司 | L280: 河南农业大学 | M280: 2007/07/01 | N280: 电子信息工程 | O280: 学士 | P280: 410221198311293839 | Q280: 2019/04/15
A281: 李月亭 | B281: 本科 | C281: 1998/04/19 | D281: 2020/07/20 | E281: 云网数据科学中心 | F281: 合成作战数据智能运营部 | G281: 系统运营经理 | H281: 山东省 | I281: 济南市 | J281: 济南 | K281: 恒安嘉新（北京）科技股份公司 | L281: 山东科技大学 | M281: 2023/07/01 | N281: 计算机科学与技术 | O281: 学士 | P281: 372328199804192730 | Q281: 2025/11/03
A282: 李跃波 | B282: 本科 | C282: 1982/04/12 | D282: 2005/08/01 | E282: 云网数据科学中心 | F282: 产品全连接全生命周期研用部 | G282: 项目经理 | H282: 山西省 | I282: 太原市 | J282: 北京 | K282: 恒安嘉新（北京）科技股份公司 | L282: 郑州大学 | M282: 2019/07/01 | N282: 计算机科学与技术 | O282: 学士 | P282: 13042919820412003X | Q282: 2021/03/30
A283: 李运菊 | B283: 本科 | C283: 2003/03/30 | D283: 2024/01/08 | E283: 云网数据科学中心 | F283: 合成作战数据智能运营部 | G283: 系统运营经理 | H283: 海南省 | I283: 海口市 | J283: 海口 | K283: 恒安嘉新（北京）科技股份公司 | L283: 保定理工学院 | M283: 2023/07/01 | N283: 计算机科学与技术 | O283: 学士 | P283: 469003200303301927 | Q283: 2026/03/02
A284: 李振威 | B284: 本科 | C284: 1986/06/07 | D284: 2009/09/01 | E284: 数据智能采集与标注研发中心 | F284: 数据智能基础采集优化部 | G284: 产品经理 | H284: 辽宁省 | I284: 沈阳市 | J284: 沈阳 | K284: 恒安嘉新（北京）科技股份公司 | L284: 辽宁工程技术大学 | M284: 2009/07/31 | N284: 通信工程 | O284: 学士 | P284: 210104198606076138 | Q284: 2018/09/03
A285: 李智 | B285: 本科 | C285: 1980/04/22 | D285: 2000/07/01 | E285: 云网数据科学中心 | F285: 咨询交付服务增长部 | G285: 解决方案经理 | H285: 北京市 | I285: 北京市 | J285: 北京 | K285: 恒安嘉新（北京）科技股份公司 | L285: 北京林业大学 | M285: 2004/07/01 | N285: 计算机科技与技术 | O285: 无 | P285: 140402198004223212 | Q285: 2020/06/28
A286: 李梓萌 | B286: 硕士研究生 | C286: 2000/01/03 | D286: 2025/09/01 | E286: 云网数据科学中心 | F286: 可信数据空间研发部 | G286: AI算法工程师 | H286: 北京市 | I286: 北京市 | J286: 北京 | K286: 恒安嘉新（北京）科技股份公司 | L286: 圣路易斯华盛顿大学 | M286: 2025/05/09 | N286: 数据分析与统计 | O286: 硕士 | P286: 210204200001035662 | Q286: 2025/09/01
A287: 李祖华 | B287: 本科 | C287: 1986/03/15 | D287: 2010/05/05 | E287: 市场连锁经营中心 | F287: 西藏-销售 | G287: 区域首席客户经理 | H287: 西藏自治区 | I287: 拉萨市 | J287: 拉萨 | K287: 恒安嘉新（北京）科技股份公司 | L287: 西藏大学 | M287: 2009/07/01 | N287: 电子信息工程 | O287: 学士 | P287: 500225198603154512 | Q287: 2022/05/13
... A313: 刘积磊 | B313: 本科 | C313: 1992/04/19 | D313: 2015/08/24 | E313: 数据智能采集与标注研发中心 | F313: 数据智能基础采集研发部 | G313: 资深C语言工程师 | H313: 天津市 | I313: 天津市 | J313: 北京 | K313: 恒安嘉新（北京）科技股份公司 | L313: 哈尔滨工程大学 | M313: 2016/07/12 | N313: 通信工程 | O313: 学士 | P313: 210623199204194917 | Q313: 2022/01/10
A314: 刘家楠 | B314: 本科 | C314: 1996/05/06 | D314: 2018/10/08 | E314: 保密管理办公室 | G314: 保密专员 | H314: 北京市 | I314: 北京市 | J314: 北京 | K314: 恒安嘉新（北京）科技股份公司 | L314: 福建师范大学福清校区 | M314: 2019/06/23 | N314: 网络工程 | O314: 学士 | P314: 341225199605068621 | Q314: 2019/12/11
A315: 刘嘉伟 | B315: 本科 | C315: 1994/09/09 | D315: 2017/06/30 | E315: 云网数据科学中心 | F315: 合成作战数据智能运营部 | G315: 系统运营经理 | H315: 新疆维吾尔自治区 | I315: 乌鲁木齐市 | J315: 乌鲁木齐 | K315: 恒安嘉新（北京）科技股份公司 | L315: 新疆大学 | M315: 2017/06/17 | N315: 计算机科学与技术 | O315: 学士 | P315: 65230219940909283X | Q315: 2025/03/24
A316: 刘杰 | B316: 大专及其以下 | C316: 1980/10/07 | D316: 2002/12/10 | E316: 云网数据科学中心 | F316: 基础网络算力工程部 | G316: 实施运维工程师 | H316: 北京市 | I316: 北京市 | J316: 北京 | K316: 恒安嘉新（北京）科技股份公司 | L316: 北京海淀走读大学 | M316: 2002/07/31 | N316: 计算机及应用 | O316: 无 | P316: 110105198010074513 | Q316: 2017/02/20
A317: 刘景旺 | B317: 本科 | C317: 1987/08/02 | D317: 2010/01/10 | E317: 数据智能采集与标注研发中心 | F317: 数据智能基础采集研发部 | G317: 资深C语言工程师 | H317: 天津市 | I317: 天津市 | J317: 北京 | K317: 北京恒安嘉新数智科技有限公司 | L317: 黑龙江八一农垦大学 | M317: 2009/06/25 | N317: 计算机科学与技术 | O317: 学士 | P317: 130282198708021810 | Q317: 2014/08/18
A318: 刘康 | B318: 本科 | C318: 1977/03/10 | D318: 1970/01/01 | E318: 云网数据科学中心 | F318: 咨询交付服务增长部 | G318: 解决方案经理 | H318: 北京市 | I318: 北京市 | J318: 北京 | K318: 恒安嘉新（北京）科技股份公司 | L318: 北京邮电大学 | M318: 2013/11/01 | N318: 软件工程 | O318: 硕士 | P318: 371581197703100510 | Q318: 2025/05/06
A319: 刘馗铭 | B319: 本科 | C319: 1996/03/11 | D319: 2020/07/01 | E319: 数据智能采集与标注研发中心 | F319: 数据智能基础采集研发部 | G319: C语言工程师 | H319: 北京市 | I319: 北京市 | J319: 北京 | K319: 北京恒安嘉新数智科技有限公司 | L319: 长春光华学院 | M319: 2020/06/01 | N319: 物联网工程 | O319: 学士 | P319: 141181199603110097 | Q319: 2023/12/01
...

Sheet Projects
A1: Name | B1: Summary | C1: Year | D1: Begin | E1: End | F1: Scope | G1: Begin1 | H1: End1
A2: 2022上海移动技术中台 | B2: 2022上海移动技术中台 | C2: 2022 | D2: 2022.2 | E2: 2023.4 | F2: AAAA | G2: =C2&"."&RANDBETWEEN(1,8) -> 2022.8 | H2: =(C2+1)&"."&RANDBETWEEN(1,12) -> 2023.1
A3: 2023年四川分中心数据中台项目 | B3: 根据工作和业务需要，建设大数据平台，主要内容包括：一套具备数据汇聚、存储、应用、共享的清江大数据平台，包括一个网络信息安全综合数据中心、两个网络信息安全综合业务系统(网络分析系统改造、网络综合管理系统)。 | C3: 2023 | D3: 2023.1 | E3: 2024.11 | F3: AAAA | G3: =C3&"."&RANDBETWEEN(1,8) -> 2023.5 | H3: =(C3+1)&"."&RANDBETWEEN(1,12) -> 2024.4
A4: 2023年山东移动工业互联网安全态势感知互联网专线扩容项目 | B4: 2023年山东移动工业互联网安全态势感知互联网专线扩容项目 | C4: 2023 | D4: 2023.7 | E4: 2024.3 | F4: AAAA | G4: =C4&"."&RANDBETWEEN(1,8) -> 2023.1 | H4: =(C4+1)&"."&RANDBETWEEN(1,12) -> 2024.9
A5: 2023-2024年中国联通软研院数据中台数据能力数据仓库研发项目（溯源数据模型研发） | B5: 中国联通软研院数据中台数据能力数据仓库研发项目（溯源数据模型研发） | C5: 2023 | D5: 2023.2 | E5: 2024.9 | F5: AAAA | G5: =C5&"."&RANDBETWEEN(1,8) -> 2023.3 | H5: =(C5+1)&"."&RANDBETWEEN(1,12) -> 2024.7
A6: 2022江苏管局车联网安全态势感知平台 | B6: 2022江苏管局车联网安全态势感知平台 | C6: 2022 | D6: 2022.7 | E6: 2023.9 | F6: AAAA | G6: =C6&"."&RANDBETWEEN(1,8) -> 2022.6 | H6: =(C6+1)&"."&RANDBETWEEN(1,12) -> 2023.4
A7: 2022年中国电信态势感知项目 | B7: 2022年中国电信态势感知项目 | C7: 2022 | D7: 2022.7 | E7: 2023.9 | F7: AAAA | G7: =C7&"."&RANDBETWEEN(1,8) -> 2022.7 | H7: =(C7+1)&"."&RANDBETWEEN(1,12) -> 2023.2
A8: 2023年中国联通内蒙古应用安全态势感知平台研发采购项目 | B8: 2023年中国联通内蒙古应用安全态势感知平台研发采购项目 | C8: 2023 | D8: 2023.1 | E8: 2024.10 | F8: AAAA | G8: =C8&"."&RANDBETWEEN(1,8) -> 2023.6 | H8: =(C8+1)&"."&RANDBETWEEN(1,12) -> 2024.2
A9: 2023年江苏分中心无锡网信办态势感知平台四期 | B9: 2023年江苏分中心无锡网信办态势感知平台四期 | C9: 2022 | D9: 2022.1 | E9: 2023.12 | F9: AAAA | G9: =C9&"."&RANDBETWEEN(1,8) -> 2022.1 | H9: =(C9+1)&"."&RANDBETWEEN(1,12) -> 2023.2
A10: 022年中国联通软研院数据中台数据能力溯源数据采集研发项目（网络数据营销场景赋能）委托开发框架协议 | B10: 2022年中国联通软研院数据中台数据能力溯源数据采集研发项目（网络数据营销场景赋能） | C10: 2023 | D10: 2023.3 | E10: 2024.6 | F10: AAAA | G10: =C10&"."&RANDBETWEEN(1,8) -> 2023.3 | H10: =(C10+1)&"."&RANDBETWEEN(1,12) -> 2024.5
A11: 中国电信北京公司2022年5G SA移动恶意程序物联网基础安全接入和威胁监测管理升级项目-软件开发合同 | B11: 2022年北京电信物联网平台项目 | C11: 2022 | D11: 2022.5 | E11: 2023.1 | F11: AAAA | G11: =C11&"."&RANDBETWEEN(1,8) -> 2022.3 | H11: =(C11+1)&"."&RANDBETWEEN(1,12) -> 2023.10
A12: 中国移动江苏公司手机恶意软件监控系统八期工程应用软件开发采购合同 | B12: 2023年江苏移动手机恶意软件监测系统八期扩容 | C12: 2023 | D12: 2023.4 | E12: 2024.2 | F12: AAAA | G12: =C12&"."&RANDBETWEEN(1,8) -> 2023.6 | H12: =(C12+1)&"."&RANDBETWEEN(1,12) -> 2024.9
A13: 手机恶意软件监控系统开发十一期工程（CM平台）应用软件开发与系统集成服务合同 | B13: 2023年移动集团手机恶意软件监控系统十一期工程应用软件开发与系统集成服务项目（CM平台） | C13: 2023 | D13: 2023.4 | E13: 2024.4 | F13: AAAA | G13: =C13&"."&RANDBETWEEN(1,8) -> 2023.2 | H13: =(C13+1)&"."&RANDBETWEEN(1,12) -> 2024.11
... A105: 2025年部委/集团总部中国移动僵木蠕集中管理平台五期工程 | B105: 中国移动2025年至2026年僵木蠕集中管理平台五期工程采购服务合同 | C105: 2026 | D105: 2026.6 | E105: 2027.1 | F105: AAAA | G105: =C105&"."&RANDBETWEEN(1,8) -> 2026.7 | H105: =(C105+1)&"."&RANDBETWEEN(1,12) -> 2027.5
A106: 2025年河北移动恶意程序平台扩容 | B106: 移动网流量安全监测处置系统四期-安全 监测管理平台研发项目合同 | C106: 2026 | D106: 2026.8 | E106: 2027.9 | G106: =C106&"."&RANDBETWEEN(1,8) -> 2026.6 | H106: =(C106+1)&"."&RANDBETWEEN(1,12) -> 2027.10

Sheet Duty
A1: Duty | B1: Desc
A2: 项目经理 | B2: 负责项目整体统筹规划，制定项目计划与里程碑；协调甲方与项目团队资源；把控项目进度、成本与质量，解决项目中的跨部门沟通问题，确保项目按期交付。
A3: 解决方案经理 | B3: 对接甲方需求，完成系统的解决方案设计与标书编制；参与需求评审，向研发团队传递甲方核心需求；配合项目实施进行方案落地指导，完成用户培训与需求迭代。
A4: 解决方案总监 | B4: 统筹全国各区域项目解决方案的整体设计；负责高难度需求的方案攻坚，把控方案的可行性与创新性；对接甲方高层，推动解决方案的落地与合作签约。
A5: 研发经理 | B5: 负责研发团队的人员管理与任务分配；制定系统的技术架构与研发规范；参与核心模块的技术攻坚，把控研发进度与代码质量，解决研发过程中的技术问题。
A6: 大数据工程师 | B6: 负责项目的大数据建模与数据清洗；基于用户行为数据构建涉诈识别特征工程；实现大数据平台的数仓搭建与ETL任务开发，支撑反诈系统的数据分析需求。
A7: 算法工程师 | B7: 研发行为识别算法（如机器学习/深度学习模型）；优化算法模型的准确率与实时性；对接研发团队完成算法模型的工程化部署，持续迭代优化模型效果。
A8: 软件开发 | B8: 参与系统的模块开发与代码编写；根据需求文档完成功能实现与单元测试；配合测试人员修复bug，参与系统联调与上线部署，完成技术文档编写。
A9: 测试人员 | B9: 制定系统的测试计划与测试用例；执行功能测试、性能测试、兼容性测试；记录并跟踪bug，与研发团队协同修复；完成测试报告编制，确保系统上线质量。
A10: 质控工程师 | B10: 建立项目质量管控体系，制定质控标准与流程；对项目各阶段（需求/研发/实施）进行质量检查；识别质量风险并提出整改方案，推动项目整体质量提升。
A11: 运维人员 | B11: 负责系统的日常运维与监控，保障系统7*24小时稳定运行；处理系统故障与性能问题，进行系统扩容与优化；完成系统备份与灾备演练，制定运维应急预案。
A12: 项目实施人员 | B12: 负责项目现场落地、需求对接与方案执行，协调客户、研发及测试资源，完成部署、调试与培训，保障项目按期交付，处理实施问题并提供售后支持。
... A15: 软件开发人员 | B15: 根据需求与架构进行代码开发、单元测试，修复缺陷，参与技术评审与联调，遵循开发规范，保障功能实现、代码质量与项目进度。
